<report report_id="EAE38ADA" report_version="2"><file_list file_error="0" file_name="287a68ba246d7cee8426ceaa67e23ce813ea29e99566cc86b6e49b0fe556a81c.exe" file_uid="65243"><file><start_boot><field value="start_boot" /><action_list><action api_name="AnalyzeStart" call_name="" call_pid="0" call_time="12:40:57.000" err_code="0" ret_value="0" status_value="0"><apiArg_list count="0" /><exInfo_list count="0" /></action><action api_name="Fake_BeCreatedEx" call_name="1.exe" call_pid="396" call_time="12:41:02.005" err_code="0" ret_value="0" status_value="0"><apiArg_list count="0" /><exInfo_list count="5"><exInfo value="SyStem.exe" /><exInfo value="212" /><exInfo value="&quot;C:\program\1.exe&quot; " /><exInfo value="direct" /><exInfo value="C:\program\1.exe" /></exInfo_list></action><action api_name="TryToAnalyze" call_name="1.exe" call_pid="396" call_time="12:41:02.006" err_code="0" ret_value="0" status_value="0"><apiArg_list count="0" /><exInfo_list count="1"><exInfo value="C:\program\1.exe" /></exInfo_list></action><action api_name="LoadLibraryExW" call_name="1.exe" call_pid="396" call_time="12:41:02.019" err_code="0" ret_value="0" status_value="0"><apiArg_list count="3"><apiArg value="0" /><apiArg value="0" /><apiArg value="0" /></apiArg_list><exInfo_list count="3"><exInfo value="C:\WINDOWS\system32\version.dll" /><exInfo value="00077bd0000" /><exInfo value="0008000" /></exInfo_list></action><action api_name="NtQueryAttributesFile" call_name="1.exe" call_pid="396" call_time="12:41:02.021" err_code="0" ret_value="c0000034" status_value="0"><apiArg_list count="2"><apiArg value="12f5f4" /><apiArg value="12f5cc" /></apiArg_list><exInfo_list count="1"><exInfo value="C:\program\WS2_32.dll" /></exInfo_list></action><action api_name="NtQueryAttributesFile" call_name="1.exe" call_pid="396" call_time="12:41:02.022" err_code="0" ret_value="0" status_value="0"><apiArg_list count="2"><apiArg value="12f5f4" /><apiArg value="12f5cc" /></apiArg_list><exInfo_list count="1"><exInfo value="C:\WINDOWS\system32\WS2_32.dll" /></exInfo_list></action><action api_name="LoadLibraryExW" call_name="1.exe" call_pid="396" call_time="12:41:02.027" err_code="0" ret_value="0" status_value="0"><apiArg_list count="3"><apiArg value="0" /><apiArg value="0" /><apiArg value="0" /></apiArg_list><exInfo_list count="3"><exInfo value="C:\WINDOWS\system32\ws2_32.dll" /><exInfo value="00071a20000" /><exInfo value="00017000" /></exInfo_list></action><action api_name="LoadLibraryExW" call_name="1.exe" call_pid="396" call_time="12:41:02.029" err_code="0" ret_value="0" status_value="0"><apiArg_list count="3"><apiArg value="0" /><apiArg value="0" /><apiArg value="0" /></apiArg_list><exInfo_list count="3"><exInfo value="C:\WINDOWS\system32\advapi32.dll" /><exInfo value="00077da0000" /><exInfo value="000a9000" /></exInfo_list></action><action api_name="LoadLibraryExW" call_name="1.exe" call_pid="396" call_time="12:41:02.031" err_code="0" ret_value="0" status_value="0"><apiArg_list count="3"><apiArg value="0" /><apiArg value="0" /><apiArg value="0" /></apiArg_list><exInfo_list count="3"><exInfo value="C:\WINDOWS\system32\rpcrt4.dll" /><exInfo value="00077e50000" /><exInfo value="00092000" /></exInfo_list></action><action api_name="LoadLibraryExW" call_name="1.exe" call_pid="396" call_time="12:41:02.033" err_code="0" ret_value="0" status_value="0"><apiArg_list count="3"><apiArg value="0" /><apiArg value="0" /><apiArg value="0" /></apiArg_list><exInfo_list count="3"><exInfo value="C:\WINDOWS\system32\secur32.dll" /><exInfo value="00077fc0000" /><exInfo value="00011000" /></exInfo_list></action><action api_name="LoadLibraryExW" call_name="1.exe" call_pid="396" call_time="12:41:02.035" err_code="0" ret_value="0" status_value="0"><apiArg_list count="3"><apiArg value="0" /><apiArg value="0" /><apiArg value="0" /></apiArg_list><exInfo_list count="3"><exInfo value="C:\WINDOWS\system32\msvcrt.dll" /><exInfo value="00077be0000" /><exInfo value="00058000" /></exInfo_list></action><action api_name="NtQueryAttributesFile" call_name="1.exe" call_pid="396" call_time="12:41:02.037" err_code="0" ret_value="c0000034" status_value="0"><apiArg_list count="2"><apiArg value="12f2c4" /><apiArg value="12f29c" /></apiArg_list><exInfo_list count="1"><exInfo value="C:\program\WS2HELP.dll" /></exInfo_list></action><action api_name="NtQueryAttributesFile" call_name="1.exe" call_pid="396" call_time="12:41:02.038" err_code="0" ret_value="0" status_value="0"><apiArg_list count="2"><apiArg value="12f2c4" /><apiArg value="12f29c" /></apiArg_list><exInfo_list count="1"><exInfo value="C:\WINDOWS\system32\WS2HELP.dll" /></exInfo_list></action><action api_name="LoadLibraryExW" call_name="1.exe" call_pid="396" call_time="12:41:02.040" err_code="0" ret_value="0" status_value="0"><apiArg_list count="3"><apiArg value="0" /><apiArg value="0" /><apiArg value="0" /></apiArg_list><exInfo_list count="3"><exInfo value="C:\WINDOWS\system32\ws2help.dll" /><exInfo value="00071a10000" /><exInfo value="0008000" /></exInfo_list></action><action api_name="LoadLibraryExW" call_name="1.exe" call_pid="396" call_time="12:41:02.042" err_code="0" ret_value="0" status_value="0"><apiArg_list count="3"><apiArg value="0" /><apiArg value="0" /><apiArg value="0" /></apiArg_list><exInfo_list count="3"><exInfo value="C:\WINDOWS\system32\wldap32.dll" /><exInfo value="00076f30000" /><exInfo value="0002c000" /></exInfo_list></action><action api_name="LoadLibraryExW" call_name="1.exe" call_pid="396" call_time="12:41:03.044" err_code="0" ret_value="0" status_value="0"><apiArg_list count="3"><apiArg value="0" /><apiArg value="0" /><apiArg value="0" /></apiArg_list><exInfo_list count="3"><exInfo value="C:\WINDOWS\system32\user32.dll" /><exInfo value="00077d10000" /><exInfo value="00090000" /></exInfo_list></action><action api_name="LoadLibraryExW" call_name="1.exe" call_pid="396" call_time="12:41:03.046" err_code="0" ret_value="0" status_value="0"><apiArg_list count="3"><apiArg value="0" /><apiArg value="0" /><apiArg value="0" /></apiArg_list><exInfo_list count="3"><exInfo value="C:\WINDOWS\system32\gdi32.dll" /><exInfo value="00077ef0000" /><exInfo value="00049000" /></exInfo_list></action><action api_name="LoadLibraryExW" call_name="1.exe" call_pid="396" call_time="12:41:03.048" err_code="0" ret_value="0" status_value="0"><apiArg_list count="3"><apiArg value="0" /><apiArg value="0" /><apiArg value="0" /></apiArg_list><exInfo_list count="3"><exInfo value="C:\WINDOWS\system32\shell32.dll" /><exInfo value="0007d590000" /><exInfo value="0007f4000" /></exInfo_list></action><action api_name="LoadLibraryExW" call_name="1.exe" call_pid="396" call_time="12:41:03.050" err_code="0" ret_value="0" status_value="0"><apiArg_list count="3"><apiArg value="0" /><apiArg value="0" /><apiArg value="0" /></apiArg_list><exInfo_list count="3"><exInfo value="C:\WINDOWS\system32\shlwapi.dll" /><exInfo value="00077f40000" /><exInfo value="00076000" /></exInfo_list></action><action api_name="NtQueryAttributesFile" call_name="1.exe" call_pid="396" call_time="12:41:03.052" err_code="0" ret_value="c0000034" status_value="0"><apiArg_list count="2"><apiArg value="12f5f4" /><apiArg value="12f5cc" /></apiArg_list><exInfo_list count="1"><exInfo value="C:\program\IPHLPAPI.DLL" /></exInfo_list></action><action api_name="NtQueryAttributesFile" call_name="1.exe" call_pid="396" call_time="12:41:03.053" err_code="0" ret_value="0" status_value="0"><apiArg_list count="2"><apiArg value="12f5f4" /><apiArg value="12f5cc" /></apiArg_list><exInfo_list count="1"><exInfo value="C:\WINDOWS\system32\IPHLPAPI.DLL" /></exInfo_list></action><action api_name="LoadLibraryExW" call_name="1.exe" call_pid="396" call_time="12:41:03.055" err_code="0" ret_value="0" status_value="0"><apiArg_list count="3"><apiArg value="0" /><apiArg value="0" /><apiArg value="0" /></apiArg_list><exInfo_list count="3"><exInfo value="C:\WINDOWS\system32\iphlpapi.dll" /><exInfo value="00076d30000" /><exInfo value="00018000" /></exInfo_list></action><action api_name="NtReadFile" call_name="1.exe" call_pid="396" call_time="12:41:03.058" err_code="0" ret_value="0" status_value="0"><apiArg_list count="9"><apiArg value="1c" /><apiArg value="0" /><apiArg value="0" /><apiArg value="0" /><apiArg value="12fae8" /><apiArg value="12fb00" /><apiArg value="4" /><apiArg value="12fb0c" /><apiArg value="0" /></apiArg_list><exInfo_list count="1"><exInfo value="C:\program\1.exe" /></exInfo_list></action><action api_name="NtQueryAttributesFile" call_name="1.exe" call_pid="396" call_time="12:41:03.071" err_code="0" ret_value="0" status_value="0"><apiArg_list count="2"><apiArg value="12e9a4" /><apiArg value="12e97c" /></apiArg_list><exInfo_list count="1"><exInfo value="C:\WINDOWS\system32\IMM32.DLL" /></exInfo_list></action><action api_name="LoadLibraryExW" call_name="1.exe" call_pid="396" call_time="12:41:03.079" err_code="0" ret_value="0" status_value="0"><apiArg_list count="3"><apiArg value="0" /><apiArg value="0" /><apiArg value="0" /></apiArg_list><exInfo_list count="3"><exInfo value="C:\WINDOWS\system32\imm32.dll" /><exInfo value="00076300000" /><exInfo value="0001d000" /></exInfo_list></action><action api_name="NtQueryAttributesFile" call_name="1.exe" call_pid="396" call_time="12:41:03.082" err_code="7e" ret_value="0" status_value="c0000135"><apiArg_list count="2"><apiArg value="12de70" /><apiArg value="12de48" /></apiArg_list><exInfo_list count="1"><exInfo value="C:\WINDOWS\system32\IMM32.DLL" /></exInfo_list></action><action api_name="NtQueryAttributesFile" call_name="1.exe" call_pid="396" call_time="12:41:03.085" err_code="7e" ret_value="c0000034" status_value="c0000135"><apiArg_list count="2"><apiArg value="12eae8" /><apiArg value="12eac0" /></apiArg_list><exInfo_list count="1"><exInfo value="C:\program\LPK.DLL" /></exInfo_list></action><action api_name="NtQueryAttributesFile" call_name="1.exe" call_pid="396" call_time="12:41:03.086" err_code="7e" ret_value="0" status_value="c0000135"><apiArg_list count="2"><apiArg value="12eae8" /><apiArg value="12eac0" /></apiArg_list><exInfo_list count="1"><exInfo value="C:\WINDOWS\system32\LPK.DLL" /></exInfo_list></action><action api_name="LoadLibraryExW" call_name="1.exe" call_pid="396" call_time="12:41:03.088" err_code="0" ret_value="0" status_value="0"><apiArg_list count="3"><apiArg value="0" /><apiArg value="0" /><apiArg value="0" /></apiArg_list><exInfo_list count="3"><exInfo value="C:\WINDOWS\system32\lpk.dll" /><exInfo value="00062c20000" /><exInfo value="0009000" /></exInfo_list></action><action api_name="NtQueryAttributesFile" call_name="1.exe" call_pid="396" call_time="12:41:03.090" err_code="7e" ret_value="c0000034" status_value="c0000135"><apiArg_list count="2"><apiArg value="12e7b8" /><apiArg value="12e790" /></apiArg_list><exInfo_list count="1"><exInfo value="C:\program\USP10.dll" /></exInfo_list></action><action api_name="NtQueryAttributesFile" call_name="1.exe" call_pid="396" call_time="12:41:03.091" err_code="7e" ret_value="0" status_value="c0000135"><apiArg_list count="2"><apiArg value="12e7b8" /><apiArg value="12e790" /></apiArg_list><exInfo_list count="1"><exInfo value="C:\WINDOWS\system32\USP10.dll" /></exInfo_list></action><action api_name="LoadLibraryExW" call_name="1.exe" call_pid="396" call_time="12:41:03.093" err_code="0" ret_value="0" status_value="0"><apiArg_list count="3"><apiArg value="0" /><apiArg value="0" /><apiArg value="0" /></apiArg_list><exInfo_list count="3"><exInfo value="C:\WINDOWS\system32\usp10.dll" /><exInfo value="00073fa0000" /><exInfo value="0006b000" /></exInfo_list></action><action api_name="NtQueryAttributesFile" call_name="1.exe" call_pid="396" call_time="12:41:03.103" err_code="b7" ret_value="c0000034" status_value="0"><apiArg_list count="2"><apiArg value="12e7ec" /><apiArg value="12e7c4" /></apiArg_list><exInfo_list count="1"><exInfo value="C:\program\1.exe.Local\" /></exInfo_list></action><action api_name="NtQueryAttributesFile" call_name="1.exe" call_pid="396" call_time="12:41:03.104" err_code="b7" ret_value="0" status_value="0"><apiArg_list count="2"><apiArg value="12e834" /><apiArg value="12e804" /></apiArg_list><exInfo_list count="1"><exInfo value="C:\WINDOWS\WinSxS\x86_Microsoft.Windows.Common-Controls_6595b64144ccf1df_6.0.2600.5512_x-ww_35d4ce83" /></exInfo_list></action><action api_name="LoadLibraryExW" call_name="1.exe" call_pid="396" call_time="12:41:03.108" err_code="0" ret_value="0" status_value="0"><apiArg_list count="3"><apiArg value="0" /><apiArg value="0" /><apiArg value="0" /></apiArg_list><exInfo_list count="3"><exInfo value="C:\WINDOWS\WinSxS\x86_Microsoft.Windows.Common-Controls_6595b64144ccf1df_6.0.2600.5512_x-ww_35d4ce83\comctl32.dll" /><exInfo value="00077180000" /><exInfo value="000103000" /></exInfo_list></action><action api_name="NtQueryAttributesFile" call_name="1.exe" call_pid="396" call_time="12:41:03.110" err_code="b7" ret_value="0" status_value="0"><apiArg_list count="2"><apiArg value="12e448" /><apiArg value="12e420" /></apiArg_list><exInfo_list count="1"><exInfo value="C:\WINDOWS\WindowsShell.Manifest" /></exInfo_list></action><action api_name="NtReadFile" call_name="1.exe" call_pid="396" call_time="12:41:03.115" err_code="0" ret_value="40" status_value="0"><apiArg_list count="16"><apiArg value="48" /><apiArg value="0" /><apiArg value="2" /><apiArg value="0" /><apiArg value="0" /><apiArg value="0" /><apiArg value="0" /><apiArg value="0" /><apiArg value="0" /><apiArg value="154318" /><apiArg value="12e61a" /><apiArg value="2080000" /><apiArg value="12e604" /><apiArg value="a0008" /><apiArg value="7c814e90" /><apiArg value="0" /></apiArg_list><exInfo_list count="1"><exInfo value="C:\WINDOWS\WindowsShell.Manifest" /></exInfo_list></action><action api_name="LoadLibraryExW" call_name="1.exe" call_pid="396" call_time="12:41:03.127" err_code="0" ret_value="0" status_value="0"><apiArg_list count="3"><apiArg value="0" /><apiArg value="0" /><apiArg value="0" /></apiArg_list><exInfo_list count="3"><exInfo value="C:\WINDOWS\system32\comctl32.dll" /><exInfo value="0005d170000" /><exInfo value="0009a000" /></exInfo_list></action><action api_name="NtQueryAttributesFile" call_name="1.exe" call_pid="396" call_time="12:41:03.162" err_code="b7" ret_value="0" status_value="0"><apiArg_list count="2"><apiArg value="12f9dc" /><apiArg value="12f9b4" /></apiArg_list><exInfo_list count="1"><exInfo value="C:\Documents and Settings\admin\Application Data" /></exInfo_list></action><action api_name="NtSetValueKey" call_name="1.exe" call_pid="396" call_time="12:41:03.163" err_code="b7" ret_value="0" status_value="0"><apiArg_list count="6"><apiArg value="78" /><apiArg value="12fc20" /><apiArg value="0" /><apiArg value="1" /><apiArg value="12fcf0" /><apiArg value="64" /></apiArg_list><exInfo_list count="2"><exInfo value="HKEY_CURRENT_USER\S-1-5-21-117609710-838170752-515967899-1003\SOFTWARE\MICROSOFT\WINDOWS\CURRENTVERSION\EXPLORER\SHELL FOLDERS" /><exInfo value="AppData" /></exInfo_list></action><action api_name="NtCreateFile" call_name="1.exe" call_pid="396" call_time="12:41:03.166" err_code="0" ret_value="c0000034" status_value="0"><apiArg_list count="11"><apiArg value="12fef0" /><apiArg value="80100080" /><apiArg value="12fe90" /><apiArg value="12fec8" /><apiArg value="0" /><apiArg value="80" /><apiArg value="3" /><apiArg value="1" /><apiArg value="60" /><apiArg value="0" /><apiArg value="0" /></apiArg_list><exInfo_list count="1"><exInfo value="C:\Documents and Settings\admin\Application Data\Wplugin.dll" /></exInfo_list></action><action api_name="NtReadFile" call_name="1.exe" call_pid="396" call_time="12:41:03.169" err_code="0" ret_value="0" status_value="c0000034"><apiArg_list count="9"><apiArg value="78" /><apiArg value="0" /><apiArg value="0" /><apiArg value="0" /><apiArg value="12feec" /><apiArg value="9b0000" /><apiArg value="2e0" /><apiArg value="0" /><apiArg value="0" /></apiArg_list><exInfo_list count="1"><exInfo value="C:\program\1.exe" /></exInfo_list></action><action api_name="Fake_WritePEFile" call_name="1.exe" call_pid="396" call_time="12:41:03.170" err_code="0" ret_value="0" status_value="c0000034"><apiArg_list count="9"><apiArg value="7c" /><apiArg value="0" /><apiArg value="0" /><apiArg value="0" /><apiArg value="12fef4" /><apiArg value="9b0000" /><apiArg value="1000" /><apiArg value="0" /><apiArg value="0" /></apiArg_list><exInfo_list count="1"><exInfo value="C:\Documents and Settings\admin\Application Data\Wplugin.dll" /></exInfo_list></action><action api_name="NtReadFile" call_name="1.exe" call_pid="396" call_time="12:41:03.171" err_code="0" ret_value="0" status_value="c0000034"><apiArg_list count="9"><apiArg value="78" /><apiArg value="0" /><apiArg value="0" /><apiArg value="0" /><apiArg value="12feec" /><apiArg value="9b0000" /><apiArg value="1180b" /><apiArg value="0" /><apiArg value="0" /></apiArg_list><exInfo_list count="1"><exInfo value="C:\program\1.exe" /></exInfo_list></action><action api_name="Fake_WritePEFile" call_name="1.exe" call_pid="396" call_time="12:41:03.172" err_code="0" ret_value="0" status_value="c0000034"><apiArg_list count="9"><apiArg value="7c" /><apiArg value="0" /><apiArg value="0" /><apiArg value="0" /><apiArg value="12fef4" /><apiArg value="9b0000" /><apiArg value="12000" /><apiArg value="0" /><apiArg value="0" /></apiArg_list><exInfo_list count="1"><exInfo value="C:\Documents and Settings\admin\Application Data\Wplugin.dll" /></exInfo_list></action><action api_name="NtReadFile" call_name="1.exe" call_pid="396" call_time="12:41:03.173" err_code="0" ret_value="0" status_value="c0000034"><apiArg_list count="9"><apiArg value="78" /><apiArg value="0" /><apiArg value="0" /><apiArg value="0" /><apiArg value="12feec" /><apiArg value="9b0000" /><apiArg value="1849" /><apiArg value="0" /><apiArg value="0" /></apiArg_list><exInfo_list count="1"><exInfo value="C:\program\1.exe" /></exInfo_list></action><action api_name="Fake_WritePEFile" call_name="1.exe" call_pid="396" call_time="12:41:03.174" err_code="0" ret_value="0" status_value="c0000034"><apiArg_list count="9"><apiArg value="7c" /><apiArg value="0" /><apiArg value="0" /><apiArg value="0" /><apiArg value="12fef4" /><apiArg value="9b0000" /><apiArg value="2000" /><apiArg value="0" /><apiArg value="0" /></apiArg_list><exInfo_list count="1"><exInfo value="C:\Documents and Settings\admin\Application Data\Wplugin.dll" /></exInfo_list></action><action api_name="NtReadFile" call_name="1.exe" call_pid="396" call_time="12:41:03.175" err_code="0" ret_value="0" status_value="c0000034"><apiArg_list count="9"><apiArg value="78" /><apiArg value="0" /><apiArg value="0" /><apiArg value="0" /><apiArg value="12feec" /><apiArg value="9b0000" /><apiArg value="27f7" /><apiArg value="0" /><apiArg value="0" /></apiArg_list><exInfo_list count="1"><exInfo value="C:\program\1.exe" /></exInfo_list></action><action api_name="Fake_WritePEFile" call_name="1.exe" call_pid="396" call_time="12:41:03.176" err_code="0" ret_value="0" status_value="c0000034"><apiArg_list count="9"><apiArg value="7c" /><apiArg value="0" /><apiArg value="0" /><apiArg value="0" /><apiArg value="12fef4" /><apiArg value="9b0000" /><apiArg value="3000" /><apiArg value="0" /><apiArg value="0" /></apiArg_list><exInfo_list count="1"><exInfo value="C:\Documents and Settings\admin\Application Data\Wplugin.dll" /></exInfo_list></action><action api_name="NtReadFile" call_name="1.exe" call_pid="396" call_time="12:41:03.177" err_code="0" ret_value="0" status_value="c0000034"><apiArg_list count="9"><apiArg value="78" /><apiArg value="0" /><apiArg value="0" /><apiArg value="0" /><apiArg value="12feec" /><apiArg value="9b0000" /><apiArg value="411" /><apiArg value="0" /><apiArg value="0" /></apiArg_list><exInfo_list count="1"><exInfo value="C:\program\1.exe" /></exInfo_list></action><action api_name="Fake_WritePEFile" call_name="1.exe" call_pid="396" call_time="12:41:03.178" err_code="0" ret_value="0" status_value="c0000034"><apiArg_list count="9"><apiArg value="7c" /><apiArg value="0" /><apiArg value="0" /><apiArg value="0" /><apiArg value="12fef4" /><apiArg value="9b0000" /><apiArg value="1000" /><apiArg value="0" /><apiArg value="0" /></apiArg_list><exInfo_list count="1"><exInfo value="C:\Documents and Settings\admin\Application Data\Wplugin.dll" /></exInfo_list></action><action api_name="NtReadFile" call_name="1.exe" call_pid="396" call_time="12:41:03.179" err_code="0" ret_value="0" status_value="c0000034"><apiArg_list count="9"><apiArg value="78" /><apiArg value="0" /><apiArg value="0" /><apiArg value="0" /><apiArg value="12feec" /><apiArg value="9b0000" /><apiArg value="df3" /><apiArg value="0" /><apiArg value="0" /></apiArg_list><exInfo_list count="1"><exInfo value="C:\program\1.exe" /></exInfo_list></action><action api_name="Fake_WritePEFile" call_name="1.exe" call_pid="396" call_time="12:41:03.180" err_code="0" ret_value="0" status_value="c0000034"><apiArg_list count="9"><apiArg value="7c" /><apiArg value="0" /><apiArg value="0" /><apiArg value="0" /><apiArg value="12fef4" /><apiArg value="9b0000" /><apiArg value="2000" /><apiArg value="0" /><apiArg value="0" /></apiArg_list><exInfo_list count="1"><exInfo value="C:\Documents and Settings\admin\Application Data\Wplugin.dll" /></exInfo_list></action><action api_name="NtQueryAttributesFile" call_name="1.exe" call_pid="396" call_time="12:41:03.183" err_code="0" ret_value="0" status_value="c0000034"><apiArg_list count="2"><apiArg value="12f5fc" /><apiArg value="12f5d4" /></apiArg_list><exInfo_list count="1"><exInfo value="C:\Documents and Settings\admin\Application Data\Wplugin.dll" /></exInfo_list></action><action api_name="LoadLibraryExW" call_name="1.exe" call_pid="396" call_time="12:41:03.189" err_code="0" ret_value="0" status_value="0"><apiArg_list count="3"><apiArg value="0" /><apiArg value="0" /><apiArg value="0" /></apiArg_list><exInfo_list count="3"><exInfo value="C:\Documents and Settings\admin\Application Data\Wplugin.dll" /><exInfo value="00010000000" /><exInfo value="0001c000" /></exInfo_list></action><action api_name="NtQueryAttributesFile" call_name="1.exe" call_pid="396" call_time="12:41:03.200" err_code="3f0" ret_value="0" status_value="c000007c"><apiArg_list count="2"><apiArg value="c4f824" /><apiArg value="c4f7fc" /></apiArg_list><exInfo_list count="1"><exInfo value="C:\WINDOWS" /></exInfo_list></action><action api_name="NtReadFile" call_name="1.exe" call_pid="396" call_time="12:41:03.197" err_code="0" ret_value="0" status_value="c0000008"><apiArg_list count="9"><apiArg value="7c" /><apiArg value="0" /><apiArg value="0" /><apiArg value="0" /><apiArg value="12fea4" /><apiArg value="a50790" /><apiArg value="60" /><apiArg value="0" /><apiArg value="0" /></apiArg_list><exInfo_list count="1"><exInfo value="C:\program\1.exe" /></exInfo_list></action><action api_name="Fake_WritePEFile" call_name="1.exe" call_pid="396" call_time="12:41:03.210" err_code="0" ret_value="0" status_value="c000007c"><apiArg_list count="9"><apiArg value="84" /><apiArg value="0" /><apiArg value="0" /><apiArg value="0" /><apiArg value="c4f1c8" /><apiArg value="9d0000" /><apiArg value="10000" /><apiArg value="0" /><apiArg value="0" /></apiArg_list><exInfo_list count="1"><exInfo value="C:\WINDOWS\Wplugin.dll" /></exInfo_list></action><action api_name="CopyFileExW" call_name="1.exe" call_pid="396" call_time="12:41:03.201" err_code="0" ret_value="1" status_value="c000007c"><apiArg_list count="6"><apiArg value="7ffdec00" /><apiArg value="153bb0" /><apiArg value="0" /><apiArg value="0" /><apiArg value="0" /><apiArg value="1" /></apiArg_list><exInfo_list count="2"><exInfo value="C:\Documents and Settings\admin\Application Data\Wplugin.dll" /><exInfo value="C:\WINDOWS\Wplugin.dll" /></exInfo_list></action><action api_name="NtQueryAttributesFile" call_name="1.exe" call_pid="396" call_time="12:41:03.216" err_code="0" ret_value="0" status_value="c000007c"><apiArg_list count="2"><apiArg value="c4f824" /><apiArg value="c4f7fc" /></apiArg_list><exInfo_list count="1"><exInfo value="C:\WINDOWS\system32" /></exInfo_list></action><action api_name="NtReadFile" call_name="1.exe" call_pid="396" call_time="12:41:03.219" err_code="0" ret_value="0" status_value="c000007c"><apiArg_list count="9"><apiArg value="84" /><apiArg value="0" /><apiArg value="0" /><apiArg value="0" /><apiArg value="c4fbd0" /><apiArg value="a51fb0" /><apiArg value="40" /><apiArg value="0" /><apiArg value="0" /></apiArg_list><exInfo_list count="1"><exInfo value="C:\WINDOWS\Wplugin.dll" /></exInfo_list></action><action api_name="NtQueryAttributesFile" call_name="1.exe" call_pid="396" call_time="12:41:03.766" err_code="3" ret_value="c0000034" status_value="c0000034"><apiArg_list count="2"><apiArg value="12f4f8" /><apiArg value="12f4d0" /></apiArg_list><exInfo_list count="1"><exInfo value="C:\program\CrashReport.dll" /></exInfo_list></action><action api_name="NtQueryAttributesFile" call_name="1.exe" call_pid="396" call_time="12:41:03.767" err_code="3" ret_value="c0000034" status_value="c0000034"><apiArg_list count="2"><apiArg value="12f4f8" /><apiArg value="12f4d0" /></apiArg_list><exInfo_list count="1"><exInfo value="C:\WINDOWS\system32\CrashReport.dll" /></exInfo_list></action><action api_name="NtQueryAttributesFile" call_name="1.exe" call_pid="396" call_time="12:41:03.768" err_code="3" ret_value="c0000034" status_value="c0000034"><apiArg_list count="2"><apiArg value="12f4f8" /><apiArg value="12f4d0" /></apiArg_list><exInfo_list count="1"><exInfo value="C:\WINDOWS\system\CrashReport.dll" /></exInfo_list></action><action api_name="NtQueryAttributesFile" call_name="1.exe" call_pid="396" call_time="12:41:03.769" err_code="3" ret_value="c0000034" status_value="c0000034"><apiArg_list count="2"><apiArg value="12f4f8" /><apiArg value="12f4d0" /></apiArg_list><exInfo_list count="1"><exInfo value="C:\WINDOWS\CrashReport.dll" /></exInfo_list></action><action api_name="NtQueryAttributesFile" call_name="1.exe" call_pid="396" call_time="12:41:03.770" err_code="3" ret_value="c0000034" status_value="c0000034"><apiArg_list count="2"><apiArg value="12f4f8" /><apiArg value="12f4d0" /></apiArg_list><exInfo_list count="1"><exInfo value="C:\WINDOWS\system32\CrashReport.dll" /></exInfo_list></action><action api_name="NtQueryAttributesFile" call_name="1.exe" call_pid="396" call_time="12:41:03.771" err_code="3" ret_value="c0000034" status_value="c0000034"><apiArg_list count="2"><apiArg value="12f4f8" /><apiArg value="12f4d0" /></apiArg_list><exInfo_list count="1"><exInfo value="C:\WINDOWS\CrashReport.dll" /></exInfo_list></action><action api_name="NtQueryAttributesFile" call_name="1.exe" call_pid="396" call_time="12:41:03.772" err_code="3" ret_value="c0000034" status_value="c0000034"><apiArg_list count="2"><apiArg value="12f4f8" /><apiArg value="12f4d0" /></apiArg_list><exInfo_list count="1"><exInfo value="C:\WINDOWS\System32\Wbem\CrashReport.dll" /></exInfo_list></action><action api_name="NtQueryAttributesFile" call_name="1.exe" call_pid="396" call_time="12:41:03.773" err_code="3" ret_value="c0000034" status_value="c0000034"><apiArg_list count="2"><apiArg value="12f4f8" /><apiArg value="12f4d0" /></apiArg_list><exInfo_list count="1"><exInfo value="C:\WINDOWS\system32\WindowsPowerShell\v1.0\CrashReport.dll" /></exInfo_list></action><action api_name="NtCreateMutant" call_name="1.exe" call_pid="396" call_time="12:41:03.778" err_code="2" ret_value="0" status_value="c0000034"><apiArg_list count="4"><apiArg value="12fef4" /><apiArg value="1f0001" /><apiArg value="12fed4" /><apiArg value="1" /></apiArg_list><exInfo_list count="1"><exInfo value="GpUpdate" /></exInfo_list></action><action api_name="NtReadFile" call_name="1.exe" call_pid="396" call_time="12:41:03.781" err_code="0" ret_value="0" status_value="c000007c"><apiArg_list count="9"><apiArg value="84" /><apiArg value="0" /><apiArg value="0" /><apiArg value="0" /><apiArg value="c4fbd0" /><apiArg value="c4fc7c" /><apiArg value="1" /><apiArg value="0" /><apiArg value="0" /></apiArg_list><exInfo_list count="1"><exInfo value="C:\WINDOWS\Wplugin.dll" /></exInfo_list></action><action api_name="LoadLibraryExW" call_name="1.exe" call_pid="396" call_time="12:41:03.033" err_code="0" ret_value="0" status_value="0"><apiArg_list count="3"><apiArg value="0" /><apiArg value="0" /><apiArg value="0" /></apiArg_list><exInfo_list count="3"><exInfo value="C:\WINDOWS\system32\ole32.dll" /><exInfo value="00076990000" /><exInfo value="00013d000" /></exInfo_list></action><action api_name="NtQueryAttributesFile" call_name="1.exe" call_pid="396" call_time="12:41:03.048" err_code="2" ret_value="0" status_value="c0000034"><apiArg_list count="2"><apiArg value="d4e67c" /><apiArg value="d4e654" /></apiArg_list><exInfo_list count="1"><exInfo value="C:\WINDOWS\system32\rpcss.dll" /></exInfo_list></action><action api_name="NtReadFile" call_name="1.exe" call_pid="396" call_time="12:41:03.057" err_code="0" ret_value="0" status_value="c000007c"><apiArg_list count="9"><apiArg value="84" /><apiArg value="0" /><apiArg value="0" /><apiArg value="0" /><apiArg value="c4fbd0" /><apiArg value="c4fc7c" /><apiArg value="1" /><apiArg value="0" /><apiArg value="0" /></apiArg_list><exInfo_list count="1"><exInfo value="C:\WINDOWS\Wplugin.dll" /></exInfo_list></action><action api_name="NtQueryAttributesFile" call_name="1.exe" call_pid="396" call_time="12:41:03.780" err_code="7e" ret_value="0" status_value="c0000135"><apiArg_list count="2"><apiArg value="d4e048" /><apiArg value="d4e020" /></apiArg_list><exInfo_list count="1"><exInfo value="C:\WINDOWS\system32\MSCTF.dll" /></exInfo_list></action><action api_name="LoadLibraryExW" call_name="1.exe" call_pid="396" call_time="12:41:03.785" err_code="0" ret_value="0" status_value="0"><apiArg_list count="3"><apiArg value="0" /><apiArg value="0" /><apiArg value="0" /></apiArg_list><exInfo_list count="3"><exInfo value="C:\WINDOWS\system32\msctf.dll" /><exInfo value="00074680000" /><exInfo value="0004c000" /></exInfo_list></action><action api_name="NtQueryAttributesFile" call_name="1.exe" call_pid="396" call_time="12:41:03.787" err_code="7e" ret_value="0" status_value="c0000135"><apiArg_list count="2"><apiArg value="d4d728" /><apiArg value="d4d700" /></apiArg_list><exInfo_list count="1"><exInfo value="C:\WINDOWS\system32\ntdll.dll" /></exInfo_list></action><action api_name="NtQueryAttributesFile" call_name="1.exe" call_pid="396" call_time="12:41:03.789" err_code="7e" ret_value="0" status_value="c0000135"><apiArg_list count="2"><apiArg value="d4d730" /><apiArg value="d4d708" /></apiArg_list><exInfo_list count="1"><exInfo value="C:\WINDOWS\system32\imm32.dll" /></exInfo_list></action><action api_name="NtReadFile" call_name="1.exe" call_pid="396" call_time="12:41:03.791" err_code="0" ret_value="0" status_value="c000007c"><apiArg_list count="9"><apiArg value="84" /><apiArg value="0" /><apiArg value="0" /><apiArg value="0" /><apiArg value="c4fbd0" /><apiArg value="c4fc7c" /><apiArg value="1" /><apiArg value="0" /><apiArg value="0" /></apiArg_list><exInfo_list count="1"><exInfo value="C:\WINDOWS\Wplugin.dll" /></exInfo_list></action><action api_name="NtCreateMutant" call_name="1.exe" call_pid="396" call_time="12:41:03.495" err_code="b7" ret_value="40000000" status_value="0"><apiArg_list count="4"><apiArg value="d4e0cc" /><apiArg value="1f0001" /><apiArg value="d4e0ac" /><apiArg value="0" /></apiArg_list><exInfo_list count="1"><exInfo value="CTF.LBES.MutexDefaultS-1-5-21-117609710-838170752-515967899-1003" /></exInfo_list></action><action api_name="NtCreateMutant" call_name="1.exe" call_pid="396" call_time="12:41:03.496" err_code="b7" ret_value="40000000" status_value="0"><apiArg_list count="4"><apiArg value="d4e0cc" /><apiArg value="1f0001" /><apiArg value="d4e0ac" /><apiArg value="0" /></apiArg_list><exInfo_list count="1"><exInfo value="CTF.Compart.MutexDefaultS-1-5-21-117609710-838170752-515967899-1003" /></exInfo_list></action><action api_name="NtCreateMutant" call_name="1.exe" call_pid="396" call_time="12:41:03.497" err_code="b7" ret_value="40000000" status_value="0"><apiArg_list count="4"><apiArg value="d4e0cc" /><apiArg value="1f0001" /><apiArg value="d4e0ac" /><apiArg value="0" /></apiArg_list><exInfo_list count="1"><exInfo value="CTF.Asm.MutexDefaultS-1-5-21-117609710-838170752-515967899-1003" /></exInfo_list></action><action api_name="NtCreateMutant" call_name="1.exe" call_pid="396" call_time="12:41:03.498" err_code="b7" ret_value="40000000" status_value="0"><apiArg_list count="4"><apiArg value="d4e0cc" /><apiArg value="1f0001" /><apiArg value="d4e0ac" /><apiArg value="0" /></apiArg_list><exInfo_list count="1"><exInfo value="CTF.Layouts.MutexDefaultS-1-5-21-117609710-838170752-515967899-1003" /></exInfo_list></action><action api_name="NtCreateMutant" call_name="1.exe" call_pid="396" call_time="12:41:03.499" err_code="b7" ret_value="40000000" status_value="0"><apiArg_list count="4"><apiArg value="d4e0cc" /><apiArg value="1f0001" /><apiArg value="d4e0ac" /><apiArg value="0" /></apiArg_list><exInfo_list count="1"><exInfo value="CTF.TMD.MutexDefaultS-1-5-21-117609710-838170752-515967899-1003" /></exInfo_list></action><action api_name="NtQueryAttributesFile" call_name="1.exe" call_pid="396" call_time="12:41:03.501" err_code="b7" ret_value="0" status_value="0"><apiArg_list count="2"><apiArg value="d4d67c" /><apiArg value="d4d654" /></apiArg_list><exInfo_list count="1"><exInfo value="C:\WINDOWS\system32\KERNEL32.dll" /></exInfo_list></action><action api_name="NtCreateMutant" call_name="1.exe" call_pid="396" call_time="12:41:03.503" err_code="0" ret_value="40000000" status_value="c0000034"><apiArg_list count="4"><apiArg value="d4e448" /><apiArg value="1f0001" /><apiArg value="d4e428" /><apiArg value="0" /></apiArg_list><exInfo_list count="1"><exInfo value="CTF.TimListCache.FMPDefaultS-1-5-21-117609710-838170752-515967899-1003MUTEX.DefaultS-1-5-21-117609710-838170752-515967899-1003" /></exInfo_list></action><action api_name="NtReadFile" call_name="1.exe" call_pid="396" call_time="12:41:03.507" err_code="0" ret_value="0" status_value="c000007c"><apiArg_list count="9"><apiArg value="84" /><apiArg value="0" /><apiArg value="0" /><apiArg value="0" /><apiArg value="c4fbd0" /><apiArg value="c4fc7c" /><apiArg value="1" /><apiArg value="0" /><apiArg value="0" /></apiArg_list><exInfo_list count="1"><exInfo value="C:\WINDOWS\Wplugin.dll" /></exInfo_list></action><action api_name="NtQueryAttributesFile" call_name="1.exe" call_pid="396" call_time="12:41:03.843" err_code="0" ret_value="0" status_value="0"><apiArg_list count="2"><apiArg value="d4e000" /><apiArg value="d4dfd8" /></apiArg_list><exInfo_list count="1"><exInfo value="C:\WINDOWS\system32\SHELL32.dll" /></exInfo_list></action><action api_name="NtQueryAttributesFile" call_name="1.exe" call_pid="396" call_time="12:41:03.846" err_code="2" ret_value="c0000034" status_value="c0000034"><apiArg_list count="2"><apiArg value="d4e444" /><apiArg value="d4e41c" /></apiArg_list><exInfo_list count="1"><exInfo value="C:\program\SETUPAPI.dll" /></exInfo_list></action><action api_name="NtQueryAttributesFile" call_name="1.exe" call_pid="396" call_time="12:41:03.847" err_code="2" ret_value="0" status_value="c0000034"><apiArg_list count="2"><apiArg value="d4e444" /><apiArg value="d4e41c" /></apiArg_list><exInfo_list count="1"><exInfo value="C:\WINDOWS\system32\SETUPAPI.dll" /></exInfo_list></action><action api_name="LoadLibraryExW" call_name="1.exe" call_pid="396" call_time="12:41:03.849" err_code="0" ret_value="0" status_value="0"><apiArg_list count="3"><apiArg value="0" /><apiArg value="0" /><apiArg value="0" /></apiArg_list><exInfo_list count="3"><exInfo value="C:\WINDOWS\system32\setupapi.dll" /><exInfo value="00076060000" /><exInfo value="000156000" /></exInfo_list></action><action api_name="NtQueryAttributesFile" call_name="1.exe" call_pid="396" call_time="12:41:03.865" err_code="0" ret_value="0" status_value="c0000034"><apiArg_list count="2"><apiArg value="d4e1fc" /><apiArg value="d4e1d4" /></apiArg_list><exInfo_list count="1"><exInfo value="C:\WINDOWS\" /></exInfo_list></action><action api_name="GetComputerNameExW" call_name="1.exe" call_pid="396" call_time="12:41:03.866" err_code="cb" ret_value="1" status_value="c0000100"><apiArg_list count="3"><apiArg value="0" /><apiArg value="d4e28c" /><apiArg value="d4e288" /></apiArg_list><exInfo_list count="0" /></action><action api_name="NtReadFile" call_name="1.exe" call_pid="396" call_time="12:41:03.874" err_code="0" ret_value="0" status_value="c000007c"><apiArg_list count="9"><apiArg value="84" /><apiArg value="0" /><apiArg value="0" /><apiArg value="0" /><apiArg value="c4fbd0" /><apiArg value="c4fc7c" /><apiArg value="1" /><apiArg value="0" /><apiArg value="0" /></apiArg_list><exInfo_list count="1"><exInfo value="C:\WINDOWS\Wplugin.dll" /></exInfo_list></action><action api_name="Fake_DetectDebugger" call_name="1.exe" call_pid="396" call_time="12:41:04.607" err_code="0" ret_value="1" status_value="c0000034"><apiArg_list count="1"><apiArg value="d4e5f4" /></apiArg_list><exInfo_list count="1"><exInfo value="MemoryOperation" /></exInfo_list></action><action api_name="GetComputerNameW" call_name="1.exe" call_pid="396" call_time="12:41:04.611" err_code="cb" ret_value="1" status_value="c0000100"><apiArg_list count="2"><apiArg value="77edb3ec" /><apiArg value="77edb070" /></apiArg_list><exInfo_list count="0" /></action><action api_name="NtWriteFile" call_name="1.exe" call_pid="396" call_time="12:41:04.620" err_code="0" ret_value="0" status_value="c000007c"><apiArg_list count="9"><apiArg value="100" /><apiArg value="e1" /><apiArg value="0" /><apiArg value="0" /><apiArg value="d4e470" /><apiArg value="15d778" /><apiArg value="48" /><apiArg value="d4e440" /><apiArg value="0" /></apiArg_list><exInfo_list count="1"><exInfo value="NamedPipe\lsarpc" /></exInfo_list></action><action api_name="NtReadFile" call_name="1.exe" call_pid="396" call_time="12:41:04.621" err_code="0" ret_value="0" status_value="c000007c"><apiArg_list count="9"><apiArg value="100" /><apiArg value="e1" /><apiArg value="0" /><apiArg value="0" /><apiArg value="15d6cc" /><apiArg value="15d888" /><apiArg value="400" /><apiArg value="d4e444" /><apiArg value="0" /></apiArg_list><exInfo_list count="1"><exInfo value="NamedPipe\lsarpc" /></exInfo_list></action><action api_name="NtWriteFile" call_name="1.exe" call_pid="396" call_time="12:41:04.633" err_code="0" ret_value="0" status_value="c000007c"><apiArg_list count="9"><apiArg value="fc" /><apiArg value="e1" /><apiArg value="0" /><apiArg value="0" /><apiArg value="d4e470" /><apiArg value="15d778" /><apiArg value="48" /><apiArg value="d4e440" /><apiArg value="0" /></apiArg_list><exInfo_list count="1"><exInfo value="NamedPipe\lsarpc" /></exInfo_list></action><action api_name="NtReadFile" call_name="1.exe" call_pid="396" call_time="12:41:04.634" err_code="0" ret_value="0" status_value="c000007c"><apiArg_list count="9"><apiArg value="fc" /><apiArg value="e1" /><apiArg value="0" /><apiArg value="0" /><apiArg value="15d6cc" /><apiArg value="15d888" /><apiArg value="400" /><apiArg value="d4e444" /><apiArg value="0" /></apiArg_list><exInfo_list count="1"><exInfo value="NamedPipe\lsarpc" /></exInfo_list></action><action api_name="NtAdjustPrivilegesToken" call_name="1.exe" call_pid="396" call_time="12:41:04.640" err_code="abadbeef" ret_value="abadbeef" status_value="abadbeef"><apiArg_list count="6"><apiArg value="fc" /><apiArg value="0" /><apiArg value="15d4a8" /><apiArg value="0" /><apiArg value="0" /><apiArg value="0" /></apiArg_list><exInfo_list count="0" /></action><action api_name="NtReadFile" call_name="1.exe" call_pid="396" call_time="12:41:04.602" err_code="0" ret_value="0" status_value="c000007c"><apiArg_list count="9"><apiArg value="84" /><apiArg value="0" /><apiArg value="0" /><apiArg value="0" /><apiArg value="c4fbd0" /><apiArg value="c4fc7c" /><apiArg value="1" /><apiArg value="0" /><apiArg value="0" /></apiArg_list><exInfo_list count="1"><exInfo value="C:\WINDOWS\Wplugin.dll" /></exInfo_list></action><action api_name="NtAdjustPrivilegesToken" call_name="1.exe" call_pid="396" call_time="12:41:04.156" err_code="abadbeef" ret_value="abadbeef" status_value="abadbeef"><apiArg_list count="6"><apiArg value="104" /><apiArg value="0" /><apiArg value="15e2e0" /><apiArg value="0" /><apiArg value="0" /><apiArg value="0" /></apiArg_list><exInfo_list count="0" /></action><action api_name="NtReadFile" call_name="1.exe" call_pid="396" call_time="12:41:04.164" err_code="0" ret_value="0" status_value="c000007c"><apiArg_list count="9"><apiArg value="84" /><apiArg value="0" /><apiArg value="0" /><apiArg value="0" /><apiArg value="c4fbd0" /><apiArg value="c4fc7c" /><apiArg value="1" /><apiArg value="0" /><apiArg value="0" /></apiArg_list><exInfo_list count="1"><exInfo value="C:\WINDOWS\Wplugin.dll" /></exInfo_list></action><action api_name="NtSetValueKey" call_name="1.exe" call_pid="396" call_time="12:41:04.140" err_code="ea" ret_value="0" status_value="0"><apiArg_list count="6"><apiArg value="104" /><apiArg value="d4ec24" /><apiArg value="0" /><apiArg value="1" /><apiArg value="7d5a34b8" /><apiArg value="c" /></apiArg_list><exInfo_list count="2"><exInfo value="HKEY_CURRENT_USER\S-1-5-21-117609710-838170752-515967899-1003\SOFTWARE\MICROSOFT\WINDOWS\CURRENTVERSION\EXPLORER\MOUNTPOINTS2\{05CFC942-435A-11E6-BABC-806D6172696F}" /><exInfo value="BaseClass" /></exInfo_list></action><action api_name="NtReadFile" call_name="1.exe" call_pid="396" call_time="12:41:04.137" err_code="0" ret_value="0" status_value="c000007c"><apiArg_list count="9"><apiArg value="84" /><apiArg value="0" /><apiArg value="0" /><apiArg value="0" /><apiArg value="c4fbd0" /><apiArg value="c4fc7c" /><apiArg value="1" /><apiArg value="0" /><apiArg value="0" /></apiArg_list><exInfo_list count="1"><exInfo value="C:\WINDOWS\Wplugin.dll" /></exInfo_list></action><action api_name="NtSetValueKey" call_name="1.exe" call_pid="396" call_time="12:41:04.048" err_code="ea" ret_value="0" status_value="0"><apiArg_list count="6"><apiArg value="104" /><apiArg value="d4ec24" /><apiArg value="0" /><apiArg value="1" /><apiArg value="7d5a34b8" /><apiArg value="c" /></apiArg_list><exInfo_list count="2"><exInfo value="HKEY_CURRENT_USER\S-1-5-21-117609710-838170752-515967899-1003\SOFTWARE\MICROSOFT\WINDOWS\CURRENTVERSION\EXPLORER\MOUNTPOINTS2\{05CFC940-435A-11E6-BABC-806D6172696F}" /><exInfo value="BaseClass" /></exInfo_list></action><action api_name="NtQueryDirectoryFile" call_name="1.exe" call_pid="396" call_time="12:41:04.055" err_code="ea" ret_value="0" status_value="0"><apiArg_list count="11"><apiArg value="108" /><apiArg value="0" /><apiArg value="0" /><apiArg value="0" /><apiArg value="d4e5b0" /><apiArg value="d4e5e0" /><apiArg value="268" /><apiArg value="3" /><apiArg value="1" /><apiArg value="d4e5c8" /><apiArg value="0" /></apiArg_list><exInfo_list count="1"><exInfo value="C:\Documents and Settings" /></exInfo_list></action><action api_name="NtReadFile" call_name="1.exe" call_pid="396" call_time="12:41:04.046" err_code="0" ret_value="0" status_value="c000007c"><apiArg_list count="9"><apiArg value="84" /><apiArg value="0" /><apiArg value="0" /><apiArg value="0" /><apiArg value="c4fbd0" /><apiArg value="c4fc7c" /><apiArg value="1" /><apiArg value="0" /><apiArg value="0" /></apiArg_list><exInfo_list count="1"><exInfo value="C:\WINDOWS\Wplugin.dll" /></exInfo_list></action><action api_name="NtQueryDirectoryFile" call_name="1.exe" call_pid="396" call_time="12:41:04.448" err_code="b7" ret_value="0" status_value="c0000034"><apiArg_list count="11"><apiArg value="110" /><apiArg value="0" /><apiArg value="0" /><apiArg value="0" /><apiArg value="d4e540" /><apiArg value="d4e570" /><apiArg value="268" /><apiArg value="3" /><apiArg value="1" /><apiArg value="d4e558" /><apiArg value="0" /></apiArg_list><exInfo_list count="1"><exInfo value="C:\Documents and Settings\admin" /></exInfo_list></action><action api_name="NtQueryDirectoryFile" call_name="1.exe" call_pid="396" call_time="12:41:04.451" err_code="b7" ret_value="0" status_value="c0000034"><apiArg_list count="11"><apiArg value="110" /><apiArg value="0" /><apiArg value="0" /><apiArg value="0" /><apiArg value="d4e4dc" /><apiArg value="d4e50c" /><apiArg value="268" /><apiArg value="3" /><apiArg value="1" /><apiArg value="d4e4f4" /><apiArg value="0" /></apiArg_list><exInfo_list count="1"><exInfo value="C:\Documents and Settings\admin\Application Data" /></exInfo_list></action><action api_name="NtQueryAttributesFile" call_name="1.exe" call_pid="396" call_time="12:41:04.455" err_code="b7" ret_value="0" status_value="c0000034"><apiArg_list count="2"><apiArg value="d4d2c0" /><apiArg value="d4d298" /></apiArg_list><exInfo_list count="1"><exInfo value="C:\Documents and Settings\admin\Application Data\desktop.ini" /></exInfo_list></action><action api_name="NtReadFile" call_name="1.exe" call_pid="396" call_time="12:41:04.460" err_code="b7" ret_value="0" status_value="c0000034"><apiArg_list count="9"><apiArg value="110" /><apiArg value="0" /><apiArg value="0" /><apiArg value="0" /><apiArg value="d4d0f0" /><apiArg value="d50000" /><apiArg value="3e" /><apiArg value="0" /><apiArg value="7c885604" /></apiArg_list><exInfo_list count="1"><exInfo value="C:\Documents and Settings\admin\Application Data\desktop.ini" /></exInfo_list></action><action api_name="NtQueryAttributesFile" call_name="1.exe" call_pid="396" call_time="12:41:04.465" err_code="b7" ret_value="0" status_value="c0000034"><apiArg_list count="2"><apiArg value="d4d2a4" /><apiArg value="d4d27c" /></apiArg_list><exInfo_list count="1"><exInfo value="C:\Documents and Settings\admin\Application Data\desktop.ini" /></exInfo_list></action><action api_name="NtReadFile" call_name="1.exe" call_pid="396" call_time="12:41:04.468" err_code="0" ret_value="0" status_value="c000007c"><apiArg_list count="9"><apiArg value="84" /><apiArg value="0" /><apiArg value="0" /><apiArg value="0" /><apiArg value="c4fbd0" /><apiArg value="c4fc7c" /><apiArg value="1" /><apiArg value="0" /><apiArg value="0" /></apiArg_list><exInfo_list count="1"><exInfo value="C:\WINDOWS\Wplugin.dll" /></exInfo_list></action><action api_name="NtReadFile" call_name="1.exe" call_pid="396" call_time="12:41:04.178" err_code="b7" ret_value="0" status_value="c0000034"><apiArg_list count="9"><apiArg value="110" /><apiArg value="0" /><apiArg value="0" /><apiArg value="0" /><apiArg value="d4ce0c" /><apiArg value="d50000" /><apiArg value="3e" /><apiArg value="0" /><apiArg value="7c885604" /></apiArg_list><exInfo_list count="1"><exInfo value="C:\Documents and Settings\admin\Application Data\desktop.ini" /></exInfo_list></action><action api_name="NtQueryAttributesFile" call_name="1.exe" call_pid="396" call_time="12:41:04.182" err_code="0" ret_value="0" status_value="c0000034"><apiArg_list count="2"><apiArg value="d4d4b8" /><apiArg value="d4d490" /></apiArg_list><exInfo_list count="1"><exInfo value="C:\Documents and Settings\admin\Application Data\desktop.ini" /></exInfo_list></action><action api_name="NtReadFile" call_name="1.exe" call_pid="396" call_time="12:41:04.185" err_code="0" ret_value="0" status_value="c0000034"><apiArg_list count="9"><apiArg value="110" /><apiArg value="0" /><apiArg value="0" /><apiArg value="0" /><apiArg value="d4d9d4" /><apiArg value="d50000" /><apiArg value="3e" /><apiArg value="0" /><apiArg value="7c885604" /></apiArg_list><exInfo_list count="1"><exInfo value="C:\Documents and Settings\admin\Application Data\desktop.ini" /></exInfo_list></action><action api_name="NtReadFile" call_name="1.exe" call_pid="396" call_time="12:41:04.177" err_code="0" ret_value="0" status_value="c000007c"><apiArg_list count="9"><apiArg value="84" /><apiArg value="0" /><apiArg value="0" /><apiArg value="0" /><apiArg value="c4fbd0" /><apiArg value="c4fc7c" /><apiArg value="1" /><apiArg value="0" /><apiArg value="0" /></apiArg_list><exInfo_list count="1"><exInfo value="C:\WINDOWS\Wplugin.dll" /></exInfo_list></action><action api_name="CreateDirectoryW" call_name="1.exe" call_pid="396" call_time="12:41:04.464" err_code="3f0" ret_value="1" status_value="c000007c"><apiArg_list count="2"><apiArg value="d4fb20" /><apiArg value="0" /></apiArg_list><exInfo_list count="1"><exInfo value="\GpUpdate" /></exInfo_list></action><action api_name="NtQueryAttributesFile" call_name="1.exe" call_pid="396" call_time="12:41:04.468" err_code="7a" ret_value="c0000034" status_value="c000007c"><apiArg_list count="2"><apiArg value="d4f8a8" /><apiArg value="d4f880" /></apiArg_list><exInfo_list count="1"><exInfo value="C:\GpUpdate.xml" /></exInfo_list></action><action api_name="NtReadFile" call_name="1.exe" call_pid="396" call_time="12:41:04.463" err_code="0" ret_value="0" status_value="c000007c"><apiArg_list count="9"><apiArg value="84" /><apiArg value="0" /><apiArg value="0" /><apiArg value="0" /><apiArg value="c4fbd0" /><apiArg value="c4fc7c" /><apiArg value="1" /><apiArg value="0" /><apiArg value="0" /></apiArg_list><exInfo_list count="1"><exInfo value="C:\WINDOWS\Wplugin.dll" /></exInfo_list></action><action api_name="WSASocketW" call_name="1.exe" call_pid="396" call_time="12:41:04.029" err_code="273f" ret_value="ffffffff" status_value="0"><apiArg_list count="6"><apiArg value="17" /><apiArg value="2" /><apiArg value="0" /><apiArg value="0" /><apiArg value="0" /><apiArg value="1" /></apiArg_list><exInfo_list count="0" /></action><action api_name="NtReadFile" call_name="1.exe" call_pid="396" call_time="12:41:04.032" err_code="0" ret_value="0" status_value="c000007c"><apiArg_list count="9"><apiArg value="84" /><apiArg value="0" /><apiArg value="0" /><apiArg value="0" /><apiArg value="c4fbd0" /><apiArg value="c4fc7c" /><apiArg value="1" /><apiArg value="0" /><apiArg value="0" /></apiArg_list><exInfo_list count="1"><exInfo value="C:\WINDOWS\Wplugin.dll" /></exInfo_list></action><action api_name="NtQueryAttributesFile" call_name="1.exe" call_pid="396" call_time="12:41:04.599" err_code="0" ret_value="0" status_value="0"><apiArg_list count="2"><apiArg value="e4e818" /><apiArg value="e4e7f0" /></apiArg_list><exInfo_list count="1"><exInfo value="C:\WINDOWS\System32\mswsock.dll" /></exInfo_list></action><action api_name="LoadLibraryExW" call_name="1.exe" call_pid="396" call_time="12:41:04.604" err_code="0" ret_value="0" status_value="0"><apiArg_list count="3"><apiArg value="0" /><apiArg value="0" /><apiArg value="0" /></apiArg_list><exInfo_list count="3"><exInfo value="C:\WINDOWS\system32\mswsock.dll" /><exInfo value="000719c0000" /><exInfo value="0003e000" /></exInfo_list></action><action api_name="NtQueryAttributesFile" call_name="1.exe" call_pid="396" call_time="12:41:04.609" err_code="0" ret_value="c0000034" status_value="0"><apiArg_list count="2"><apiArg value="e4e880" /><apiArg value="e4e858" /></apiArg_list><exInfo_list count="1"><exInfo value="C:\program\DNSAPI.dll" /></exInfo_list></action><action api_name="NtQueryAttributesFile" call_name="1.exe" call_pid="396" call_time="12:41:04.610" err_code="0" ret_value="0" status_value="0"><apiArg_list count="2"><apiArg value="e4e880" /><apiArg value="e4e858" /></apiArg_list><exInfo_list count="1"><exInfo value="C:\WINDOWS\system32\DNSAPI.dll" /></exInfo_list></action><action api_name="LoadLibraryExW" call_name="1.exe" call_pid="396" call_time="12:41:04.612" err_code="0" ret_value="0" status_value="0"><apiArg_list count="3"><apiArg value="0" /><apiArg value="0" /><apiArg value="0" /></apiArg_list><exInfo_list count="3"><exInfo value="C:\WINDOWS\system32\dnsapi.dll" /><exInfo value="00076ef0000" /><exInfo value="00027000" /></exInfo_list></action><action api_name="NtReadFile" call_name="1.exe" call_pid="396" call_time="12:41:04.615" err_code="0" ret_value="0" status_value="c000007c"><apiArg_list count="9"><apiArg value="84" /><apiArg value="0" /><apiArg value="0" /><apiArg value="0" /><apiArg value="c4fbd0" /><apiArg value="c4fc7c" /><apiArg value="1" /><apiArg value="0" /><apiArg value="0" /></apiArg_list><exInfo_list count="1"><exInfo value="C:\WINDOWS\Wplugin.dll" /></exInfo_list></action><action api_name="DnsQuery_W" call_name="1.exe" call_pid="396" call_time="12:41:04.256" err_code="57" ret_value="0" status_value="0"><apiArg_list count="6"><apiArg value="719cb778" /><apiArg value="1" /><apiArg value="0" /><apiArg value="0" /><apiArg value="e4f10c" /><apiArg value="0" /></apiArg_list><exInfo_list count="1"><exInfo value="" /></exInfo_list></action><action api_name="NtReadFile" call_name="1.exe" call_pid="396" call_time="12:41:04.656" err_code="0" ret_value="0" status_value="c000007c"><apiArg_list count="9"><apiArg value="84" /><apiArg value="0" /><apiArg value="0" /><apiArg value="0" /><apiArg value="c4fbd0" /><apiArg value="c4fc7c" /><apiArg value="1" /><apiArg value="0" /><apiArg value="0" /></apiArg_list><exInfo_list count="1"><exInfo value="C:\WINDOWS\Wplugin.dll" /></exInfo_list></action><action api_name="NtWriteFile" call_name="1.exe" call_pid="396" call_time="12:41:06.196" err_code="0" ret_value="0" status_value="c000007c"><apiArg_list count="9"><apiArg value="148" /><apiArg value="0" /><apiArg value="0" /><apiArg value="0" /><apiArg value="c4fc04" /><apiArg value="100167b0" /><apiArg value="c" /><apiArg value="0" /><apiArg value="0" /></apiArg_list><exInfo_list count="1"><exInfo value="C:\WINDOWS\explorer.exe.local" /></exInfo_list></action><action api_name="Fake_WritePEFile" call_name="1.exe" call_pid="396" call_time="12:41:06.203" err_code="0" ret_value="0" status_value="c000007c"><apiArg_list count="9"><apiArg value="14c" /><apiArg value="0" /><apiArg value="0" /><apiArg value="0" /><apiArg value="c4f090" /><apiArg value="a20000" /><apiArg value="4e00" /><apiArg value="0" /><apiArg value="0" /></apiArg_list><exInfo_list count="1"><exInfo value="C:\WINDOWS\ws2help.dll" /></exInfo_list></action><action api_name="CopyFileExW" call_name="1.exe" call_pid="396" call_time="12:41:06.198" err_code="0" ret_value="1" status_value="c000007c"><apiArg_list count="6"><apiArg value="7ffdec00" /><apiArg value="15f2b0" /><apiArg value="0" /><apiArg value="0" /><apiArg value="0" /><apiArg value="1" /></apiArg_list><exInfo_list count="2"><exInfo value="C:\WINDOWS\system32\ws2help.dll" /><exInfo value="C:\WINDOWS\ws2help.dll" /></exInfo_list></action><action api_name="NtQueryAttributesFile" call_name="1.exe" call_pid="396" call_time="12:41:06.207" err_code="0" ret_value="0" status_value="c000007c"><apiArg_list count="2"><apiArg value="c4fa98" /><apiArg value="c4fa70" /></apiArg_list><exInfo_list count="1"><exInfo value="C:\WINDOWS\ws2help.dll" /></exInfo_list></action><action api_name="NtReadFile" call_name="1.exe" call_pid="396" call_time="12:41:06.210" err_code="0" ret_value="0" status_value="c000007c"><apiArg_list count="9"><apiArg value="14c" /><apiArg value="0" /><apiArg value="0" /><apiArg value="0" /><apiArg value="c4fa78" /><apiArg value="c4fb24" /><apiArg value="60" /><apiArg value="0" /><apiArg value="0" /></apiArg_list><exInfo_list count="1"><exInfo value="C:\WINDOWS\ws2help.dll" /></exInfo_list></action><action api_name="Fake_WritePEFile" call_name="1.exe" call_pid="396" call_time="12:41:06.133" err_code="0" ret_value="0" status_value="c000007c"><apiArg_list count="9"><apiArg value="14c" /><apiArg value="0" /><apiArg value="0" /><apiArg value="0" /><apiArg value="c4fa80" /><apiArg value="9b7ad0" /><apiArg value="434" /><apiArg value="0" /><apiArg value="0" /></apiArg_list><exInfo_list count="1"><exInfo value="C:\WINDOWS\ws2help.dll" /></exInfo_list></action><action api_name="Fake_SetFileCreationTime" call_name="1.exe" call_pid="396" call_time="12:41:06.139" err_code="0" ret_value="0" status_value="c000007c"><apiArg_list count="5"><apiArg value="14c" /><apiArg value="c4fabc" /><apiArg value="c4fa94" /><apiArg value="28" /><apiArg value="4" /></apiArg_list><exInfo_list count="2"><exInfo value="C:\WINDOWS\ws2help.dll" /><exInfo value="2019-03-27 12_40_59" /></exInfo_list></action><action api_name="Process32FirstW" call_name="1.exe" call_pid="396" call_time="12:41:06.142" err_code="0" ret_value="1" status_value="c000007c"><apiArg_list count="2"><apiArg value="14c" /><apiArg value="c4f698" /></apiArg_list><exInfo_list count="0" /></action><action api_name="Module32FirstW" call_name="1.exe" call_pid="396" call_time="12:41:06.144" err_code="0" ret_value="1" status_value="c000007c"><apiArg_list count="2"><apiArg value="150" /><apiArg value="c4f49c" /></apiArg_list><exInfo_list count="0" /></action><action api_name="NtReadVirtualMemory" call_name="1.exe" call_pid="396" call_time="12:41:06.158" err_code="5" ret_value="0" status_value="c0000022"><apiArg_list count="5"><apiArg value="148" /><apiArg value="7ffd900c" /><apiArg value="c4f75c" /><apiArg value="4" /><apiArg value="c4f724" /></apiArg_list><exInfo_list count="2"><exInfo value="explorer.exe" /><exInfo value="1244" /></exInfo_list></action><action api_name="NtReadVirtualMemory" call_name="1.exe" call_pid="396" call_time="12:41:06.520" err_code="5" ret_value="0" status_value="c0000022"><apiArg_list count="5"><apiArg value="150" /><apiArg value="7ffd300c" /><apiArg value="c4f75c" /><apiArg value="4" /><apiArg value="c4f724" /></apiArg_list><exInfo_list count="2"><exInfo value="ctfmon.exe" /><exInfo value="1504" /></exInfo_list></action><action api_name="NtReadVirtualMemory" call_name="1.exe" call_pid="396" call_time="12:41:06.637" err_code="5" ret_value="0" status_value="c0000022"><apiArg_list count="5"><apiArg value="148" /><apiArg value="7ffde00c" /><apiArg value="c4f75c" /><apiArg value="4" /><apiArg value="c4f724" /></apiArg_list><exInfo_list count="2"><exInfo value="reader_sl.exe" /><exInfo value="1528" /></exInfo_list></action><action api_name="NtReadVirtualMemory" call_name="1.exe" call_pid="396" call_time="12:41:06.730" err_code="5" ret_value="0" status_value="c0000022"><apiArg_list count="5"><apiArg value="150" /><apiArg value="7ffdd00c" /><apiArg value="c4f75c" /><apiArg value="4" /><apiArg value="c4f724" /></apiArg_list><exInfo_list count="2"><exInfo value="360tray.exe" /><exInfo value="-1414676753" /></exInfo_list></action><action api_name="NtReadVirtualMemory" call_name="1.exe" call_pid="396" call_time="12:41:06.731" err_code="5" ret_value="0" status_value="c0000022"><apiArg_list count="5"><apiArg value="150" /><apiArg value="251e9c" /><apiArg value="c4f790" /><apiArg value="4" /><apiArg value="c4f72c" /></apiArg_list><exInfo_list count="2"><exInfo value="360tray.exe" /><exInfo value="1564" /></exInfo_list></action><action api_name="NtReadVirtualMemory" call_name="1.exe" call_pid="396" call_time="12:41:06.751" err_code="5" ret_value="0" status_value="c0000022"><apiArg_list count="5"><apiArg value="148" /><apiArg value="7ffda00c" /><apiArg value="c4f75c" /><apiArg value="4" /><apiArg value="c4f724" /></apiArg_list><exInfo_list count="2"><exInfo value="AliIM.exe" /><exInfo value="-1414676753" /></exInfo_list></action><action api_name="NtReadVirtualMemory" call_name="1.exe" call_pid="396" call_time="12:41:06.752" err_code="5" ret_value="0" status_value="c0000022"><apiArg_list count="5"><apiArg value="148" /><apiArg value="251e9c" /><apiArg value="c4f790" /><apiArg value="4" /><apiArg value="c4f72c" /></apiArg_list><exInfo_list count="2"><exInfo value="AliIM.exe" /><exInfo value="1576" /></exInfo_list></action><action api_name="NtReadVirtualMemory" call_name="1.exe" call_pid="396" call_time="12:41:06.772" err_code="5" ret_value="0" status_value="c0000022"><apiArg_list count="5"><apiArg value="150" /><apiArg value="7ffd400c" /><apiArg value="c4f75c" /><apiArg value="4" /><apiArg value="c4f724" /></apiArg_list><exInfo_list count="2"><exInfo value="AlipaySecSvc.ex" /><exInfo value="-1414676753" /></exInfo_list></action><action api_name="NtReadVirtualMemory" call_name="1.exe" call_pid="396" call_time="12:41:06.773" err_code="5" ret_value="0" status_value="c0000022"><apiArg_list count="5"><apiArg value="150" /><apiArg value="251e9c" /><apiArg value="c4f790" /><apiArg value="4" /><apiArg value="c4f72c" /></apiArg_list><exInfo_list count="2"><exInfo value="AlipaySecSvc.exe" /><exInfo value="1588" /></exInfo_list></action><action api_name="NtReadVirtualMemory" call_name="1.exe" call_pid="396" call_time="12:41:06.793" err_code="5" ret_value="0" status_value="c0000022"><apiArg_list count="5"><apiArg value="148" /><apiArg value="7ffde00c" /><apiArg value="c4f75c" /><apiArg value="4" /><apiArg value="c4f724" /></apiArg_list><exInfo_list count="2"><exInfo value="AliWorkbench.ex" /><exInfo value="-1414676753" /></exInfo_list></action><action api_name="NtReadVirtualMemory" call_name="1.exe" call_pid="396" call_time="12:41:06.794" err_code="5" ret_value="0" status_value="c0000022"><apiArg_list count="5"><apiArg value="148" /><apiArg value="251e9c" /><apiArg value="c4f790" /><apiArg value="4" /><apiArg value="c4f72c" /></apiArg_list><exInfo_list count="2"><exInfo value="AliWorkbench.exe" /><exInfo value="1604" /></exInfo_list></action><action api_name="NtReadVirtualMemory" call_name="1.exe" call_pid="396" call_time="12:41:06.814" err_code="5" ret_value="0" status_value="c0000022"><apiArg_list count="5"><apiArg value="150" /><apiArg value="7ffdd00c" /><apiArg value="c4f75c" /><apiArg value="4" /><apiArg value="c4f724" /></apiArg_list><exInfo_list count="2"><exInfo value="avgnt.exe" /><exInfo value="-1414676753" /></exInfo_list></action><action api_name="NtReadVirtualMemory" call_name="1.exe" call_pid="396" call_time="12:41:06.815" err_code="5" ret_value="0" status_value="c0000022"><apiArg_list count="5"><apiArg value="150" /><apiArg value="251e9c" /><apiArg value="c4f790" /><apiArg value="4" /><apiArg value="c4f72c" /></apiArg_list><exInfo_list count="2"><exInfo value="avgnt.exe" /><exInfo value="1616" /></exInfo_list></action><action api_name="NtReadVirtualMemory" call_name="1.exe" call_pid="396" call_time="12:41:06.835" err_code="5" ret_value="0" status_value="c0000022"><apiArg_list count="5"><apiArg value="148" /><apiArg value="7ffd900c" /><apiArg value="c4f75c" /><apiArg value="4" /><apiArg value="c4f724" /></apiArg_list><exInfo_list count="2"><exInfo value="avp.exe" /><exInfo value="-1414676753" /></exInfo_list></action><action api_name="NtReadVirtualMemory" call_name="1.exe" call_pid="396" call_time="12:41:06.836" err_code="5" ret_value="0" status_value="c0000022"><apiArg_list count="5"><apiArg value="148" /><apiArg value="251e9c" /><apiArg value="c4f790" /><apiArg value="4" /><apiArg value="c4f72c" /></apiArg_list><exInfo_list count="2"><exInfo value="avp.exe" /><exInfo value="1628" /></exInfo_list></action><action api_name="NtReadVirtualMemory" call_name="1.exe" call_pid="396" call_time="12:41:06.856" err_code="5" ret_value="0" status_value="c0000022"><apiArg_list count="5"><apiArg value="150" /><apiArg value="7ffd600c" /><apiArg value="c4f75c" /><apiArg value="4" /><apiArg value="c4f724" /></apiArg_list><exInfo_list count="2"><exInfo value="certd_BHDC_ICBC" /><exInfo value="-1414676753" /></exInfo_list></action><action api_name="NtReadVirtualMemory" call_name="1.exe" call_pid="396" call_time="12:41:06.857" err_code="5" ret_value="0" status_value="c0000022"><apiArg_list count="5"><apiArg value="150" /><apiArg value="251e9c" /><apiArg value="c4f790" /><apiArg value="4" /><apiArg value="c4f72c" /></apiArg_list><exInfo_list count="2"><exInfo value="certd_BHDC_ICBC.exe" /><exInfo value="1640" /></exInfo_list></action><action api_name="NtReadVirtualMemory" call_name="1.exe" call_pid="396" call_time="12:41:06.877" err_code="5" ret_value="0" status_value="c0000022"><apiArg_list count="5"><apiArg value="148" /><apiArg value="7ffd300c" /><apiArg value="c4f75c" /><apiArg value="4" /><apiArg value="c4f724" /></apiArg_list><exInfo_list count="2"><exInfo value="certd_nps3000_I" /><exInfo value="-1414676753" /></exInfo_list></action><action api_name="NtReadVirtualMemory" call_name="1.exe" call_pid="396" call_time="12:41:06.878" err_code="5" ret_value="0" status_value="c0000022"><apiArg_list count="5"><apiArg value="148" /><apiArg value="251e9c" /><apiArg value="c4f790" /><apiArg value="4" /><apiArg value="c4f72c" /></apiArg_list><exInfo_list count="2"><exInfo value="certd_nps3000_ICBC.exe" /><exInfo value="1652" /></exInfo_list></action><action api_name="NtReadVirtualMemory" call_name="1.exe" call_pid="396" call_time="12:41:06.898" err_code="5" ret_value="0" status_value="c0000022"><apiArg_list count="5"><apiArg value="150" /><apiArg value="7ffda00c" /><apiArg value="c4f75c" /><apiArg value="4" /><apiArg value="c4f724" /></apiArg_list><exInfo_list count="2"><exInfo value="crossfire.exe" /><exInfo value="-1414676753" /></exInfo_list></action><action api_name="NtReadVirtualMemory" call_name="1.exe" call_pid="396" call_time="12:41:06.899" err_code="5" ret_value="0" status_value="c0000022"><apiArg_list count="5"><apiArg value="150" /><apiArg value="251e9c" /><apiArg value="c4f790" /><apiArg value="4" /><apiArg value="c4f72c" /></apiArg_list><exInfo_list count="2"><exInfo value="crossfire.exe" /><exInfo value="1668" /></exInfo_list></action><action api_name="NtReadVirtualMemory" call_name="1.exe" call_pid="396" call_time="12:41:06.919" err_code="5" ret_value="0" status_value="c0000022"><apiArg_list count="5"><apiArg value="148" /><apiArg value="7ffdf00c" /><apiArg value="c4f75c" /><apiArg value="4" /><apiArg value="c4f724" /></apiArg_list><exInfo_list count="2"><exInfo value="dnf.exe" /><exInfo value="-1414676753" /></exInfo_list></action><action api_name="NtReadVirtualMemory" call_name="1.exe" call_pid="396" call_time="12:41:06.920" err_code="5" ret_value="0" status_value="c0000022"><apiArg_list count="5"><apiArg value="148" /><apiArg value="251e9c" /><apiArg value="c4f790" /><apiArg value="4" /><apiArg value="c4f72c" /></apiArg_list><exInfo_list count="2"><exInfo value="dnf.exe" /><exInfo value="1684" /></exInfo_list></action><action api_name="NtReadVirtualMemory" call_name="1.exe" call_pid="396" call_time="12:41:06.940" err_code="5" ret_value="0" status_value="c0000022"><apiArg_list count="5"><apiArg value="150" /><apiArg value="7ffdb00c" /><apiArg value="c4f75c" /><apiArg value="4" /><apiArg value="c4f724" /></apiArg_list><exInfo_list count="2"><exInfo value="ICBCEBankAssist" /><exInfo value="-1414676753" /></exInfo_list></action><action api_name="NtReadVirtualMemory" call_name="1.exe" call_pid="396" call_time="12:41:06.941" err_code="5" ret_value="0" status_value="c0000022"><apiArg_list count="5"><apiArg value="150" /><apiArg value="251e9c" /><apiArg value="c4f790" /><apiArg value="4" /><apiArg value="c4f72c" /></apiArg_list><exInfo_list count="2"><exInfo value="ICBCEBankAssist.exe" /><exInfo value="1696" /></exInfo_list></action><action api_name="NtReadVirtualMemory" call_name="1.exe" call_pid="396" call_time="12:41:06.961" err_code="5" ret_value="0" status_value="c0000022"><apiArg_list count="5"><apiArg value="148" /><apiArg value="7ffd600c" /><apiArg value="c4f75c" /><apiArg value="4" /><apiArg value="c4f724" /></apiArg_list><exInfo_list count="2"><exInfo value="ksafe.exe" /><exInfo value="-1414676753" /></exInfo_list></action><action api_name="NtReadVirtualMemory" call_name="1.exe" call_pid="396" call_time="12:41:06.962" err_code="5" ret_value="0" status_value="c0000022"><apiArg_list count="5"><apiArg value="148" /><apiArg value="251e9c" /><apiArg value="c4f790" /><apiArg value="4" /><apiArg value="c4f72c" /></apiArg_list><exInfo_list count="2"><exInfo value="ksafe.exe" /><exInfo value="1708" /></exInfo_list></action><action api_name="NtReadVirtualMemory" call_name="1.exe" call_pid="396" call_time="12:41:06.982" err_code="5" ret_value="0" status_value="c0000022"><apiArg_list count="5"><apiArg value="150" /><apiArg value="7ffdf00c" /><apiArg value="c4f75c" /><apiArg value="4" /><apiArg value="c4f724" /></apiArg_list><exInfo_list count="2"><exInfo value="ksafesvc.exe" /><exInfo value="-1414676753" /></exInfo_list></action><action api_name="NtReadVirtualMemory" call_name="1.exe" call_pid="396" call_time="12:41:06.983" err_code="5" ret_value="0" status_value="c0000022"><apiArg_list count="5"><apiArg value="150" /><apiArg value="251e9c" /><apiArg value="c4f790" /><apiArg value="4" /><apiArg value="c4f72c" /></apiArg_list><exInfo_list count="2"><exInfo value="ksafesvc.exe" /><exInfo value="1728" /></exInfo_list></action><action api_name="NtReadVirtualMemory" call_name="1.exe" call_pid="396" call_time="12:41:06.003" err_code="5" ret_value="0" status_value="c0000022"><apiArg_list count="5"><apiArg value="148" /><apiArg value="7ffde00c" /><apiArg value="c4f75c" /><apiArg value="4" /><apiArg value="c4f724" /></apiArg_list><exInfo_list count="2"><exInfo value="ksafetray.exe" /><exInfo value="-1414676753" /></exInfo_list></action><action api_name="NtReadVirtualMemory" call_name="1.exe" call_pid="396" call_time="12:41:06.004" err_code="5" ret_value="0" status_value="c0000022"><apiArg_list count="5"><apiArg value="148" /><apiArg value="251e9c" /><apiArg value="c4f790" /><apiArg value="4" /><apiArg value="c4f72c" /></apiArg_list><exInfo_list count="2"><exInfo value="ksafetray.exe" /><exInfo value="1740" /></exInfo_list></action><action api_name="NtReadVirtualMemory" call_name="1.exe" call_pid="396" call_time="12:41:06.024" err_code="5" ret_value="0" status_value="c0000022"><apiArg_list count="5"><apiArg value="150" /><apiArg value="7ffda00c" /><apiArg value="c4f75c" /><apiArg value="4" /><apiArg value="c4f724" /></apiArg_list><exInfo_list count="2"><exInfo value="MWICBCUKeyUI.ex" /><exInfo value="-1414676753" /></exInfo_list></action><action api_name="NtReadVirtualMemory" call_name="1.exe" call_pid="396" call_time="12:41:06.025" err_code="5" ret_value="0" status_value="c0000022"><apiArg_list count="5"><apiArg value="150" /><apiArg value="251e9c" /><apiArg value="c4f790" /><apiArg value="4" /><apiArg value="c4f72c" /></apiArg_list><exInfo_list count="2"><exInfo value="MWICBCUKeyUI.exe" /><exInfo value="1752" /></exInfo_list></action><action api_name="NtReadVirtualMemory" call_name="1.exe" call_pid="396" call_time="12:41:06.045" err_code="5" ret_value="0" status_value="c0000022"><apiArg_list count="5"><apiArg value="148" /><apiArg value="7ffd600c" /><apiArg value="c4f75c" /><apiArg value="4" /><apiArg value="c4f724" /></apiArg_list><exInfo_list count="2"><exInfo value="QQ.exe" /><exInfo value="-1414676753" /></exInfo_list></action><action api_name="NtReadVirtualMemory" call_name="1.exe" call_pid="396" call_time="12:41:06.046" err_code="5" ret_value="0" status_value="c0000022"><apiArg_list count="5"><apiArg value="148" /><apiArg value="251e9c" /><apiArg value="c4f790" /><apiArg value="4" /><apiArg value="c4f72c" /></apiArg_list><exInfo_list count="2"><exInfo value="QQ.exe" /><exInfo value="1764" /></exInfo_list></action><action api_name="NtReadVirtualMemory" call_name="1.exe" call_pid="396" call_time="12:41:06.066" err_code="5" ret_value="0" status_value="c0000022"><apiArg_list count="5"><apiArg value="150" /><apiArg value="7ffd300c" /><apiArg value="c4f75c" /><apiArg value="4" /><apiArg value="c4f724" /></apiArg_list><exInfo_list count="2"><exInfo value="QQPCRTP.exe" /><exInfo value="-1414676753" /></exInfo_list></action><action api_name="NtReadVirtualMemory" call_name="1.exe" call_pid="396" call_time="12:41:06.067" err_code="5" ret_value="0" status_value="c0000022"><apiArg_list count="5"><apiArg value="150" /><apiArg value="251e9c" /><apiArg value="c4f790" /><apiArg value="4" /><apiArg value="c4f72c" /></apiArg_list><exInfo_list count="2"><exInfo value="QQPCRTP.exe" /><exInfo value="1784" /></exInfo_list></action><action api_name="NtReadVirtualMemory" call_name="1.exe" call_pid="396" call_time="12:41:06.087" err_code="5" ret_value="0" status_value="c0000022"><apiArg_list count="5"><apiArg value="148" /><apiArg value="7ffde00c" /><apiArg value="c4f75c" /><apiArg value="4" /><apiArg value="c4f724" /></apiArg_list><exInfo_list count="2"><exInfo value="QQPCTray.exe" /><exInfo value="-1414676753" /></exInfo_list></action><action api_name="NtReadVirtualMemory" call_name="1.exe" call_pid="396" call_time="12:41:06.088" err_code="5" ret_value="0" status_value="c0000022"><apiArg_list count="5"><apiArg value="148" /><apiArg value="251e9c" /><apiArg value="c4f790" /><apiArg value="4" /><apiArg value="c4f72c" /></apiArg_list><exInfo_list count="2"><exInfo value="QQPCTray.exe" /><exInfo value="1796" /></exInfo_list></action><action api_name="NtReadVirtualMemory" call_name="1.exe" call_pid="396" call_time="12:41:06.108" err_code="5" ret_value="0" status_value="c0000022"><apiArg_list count="5"><apiArg value="150" /><apiArg value="7ffde00c" /><apiArg value="c4f75c" /><apiArg value="4" /><apiArg value="c4f724" /></apiArg_list><exInfo_list count="2"><exInfo value="QQProtect.exe" /><exInfo value="-1414676753" /></exInfo_list></action><action api_name="NtReadVirtualMemory" call_name="1.exe" call_pid="396" call_time="12:41:06.109" err_code="5" ret_value="0" status_value="c0000022"><apiArg_list count="5"><apiArg value="150" /><apiArg value="251e9c" /><apiArg value="c4f790" /><apiArg value="4" /><apiArg value="c4f72c" /></apiArg_list><exInfo_list count="2"><exInfo value="QQProtect.exe" /><exInfo value="1804" /></exInfo_list></action><action api_name="NtReadVirtualMemory" call_name="1.exe" call_pid="396" call_time="12:41:06.129" err_code="5" ret_value="0" status_value="c0000022"><apiArg_list count="5"><apiArg value="148" /><apiArg value="7ffdb00c" /><apiArg value="c4f75c" /><apiArg value="4" /><apiArg value="c4f724" /></apiArg_list><exInfo_list count="2"><exInfo value="RavMon.exe" /><exInfo value="-1414676753" /></exInfo_list></action><action api_name="NtReadVirtualMemory" call_name="1.exe" call_pid="396" call_time="12:41:06.130" err_code="5" ret_value="0" status_value="c0000022"><apiArg_list count="5"><apiArg value="148" /><apiArg value="251e9c" /><apiArg value="c4f790" /><apiArg value="4" /><apiArg value="c4f72c" /></apiArg_list><exInfo_list count="2"><exInfo value="RavMon.exe" /><exInfo value="1816" /></exInfo_list></action><action api_name="NtReadVirtualMemory" call_name="1.exe" call_pid="396" call_time="12:41:06.150" err_code="5" ret_value="0" status_value="c0000022"><apiArg_list count="5"><apiArg value="150" /><apiArg value="7ffd800c" /><apiArg value="c4f75c" /><apiArg value="4" /><apiArg value="c4f724" /></apiArg_list><exInfo_list count="2"><exInfo value="RavMonD.exe" /><exInfo value="-1414676753" /></exInfo_list></action><action api_name="NtReadVirtualMemory" call_name="1.exe" call_pid="396" call_time="12:41:06.151" err_code="5" ret_value="0" status_value="c0000022"><apiArg_list count="5"><apiArg value="150" /><apiArg value="251e9c" /><apiArg value="c4f790" /><apiArg value="4" /><apiArg value="c4f72c" /></apiArg_list><exInfo_list count="2"><exInfo value="RavMonD.exe" /><exInfo value="1824" /></exInfo_list></action><action api_name="NtReadVirtualMemory" call_name="1.exe" call_pid="396" call_time="12:41:06.171" err_code="5" ret_value="0" status_value="c0000022"><apiArg_list count="5"><apiArg value="148" /><apiArg value="7ffd600c" /><apiArg value="c4f75c" /><apiArg value="4" /><apiArg value="c4f724" /></apiArg_list><exInfo_list count="2"><exInfo value="rstray.exe" /><exInfo value="-1414676753" /></exInfo_list></action><action api_name="NtReadVirtualMemory" call_name="1.exe" call_pid="396" call_time="12:41:06.172" err_code="5" ret_value="0" status_value="c0000022"><apiArg_list count="5"><apiArg value="148" /><apiArg value="251e9c" /><apiArg value="c4f790" /><apiArg value="4" /><apiArg value="c4f72c" /></apiArg_list><exInfo_list count="2"><exInfo value="rstray.exe" /><exInfo value="1836" /></exInfo_list></action><action api_name="NtReadVirtualMemory" call_name="1.exe" call_pid="396" call_time="12:41:06.192" err_code="5" ret_value="0" status_value="c0000022"><apiArg_list count="5"><apiArg value="150" /><apiArg value="7ffd300c" /><apiArg value="c4f75c" /><apiArg value="4" /><apiArg value="c4f724" /></apiArg_list><exInfo_list count="2"><exInfo value="TaoBrowser.exe" /><exInfo value="-1414676753" /></exInfo_list></action><action api_name="NtReadVirtualMemory" call_name="1.exe" call_pid="396" call_time="12:41:06.193" err_code="5" ret_value="0" status_value="c0000022"><apiArg_list count="5"><apiArg value="150" /><apiArg value="251e9c" /><apiArg value="c4f790" /><apiArg value="4" /><apiArg value="c4f72c" /></apiArg_list><exInfo_list count="2"><exInfo value="TaoBrowser.exe" /><exInfo value="1848" /></exInfo_list></action><action api_name="NtReadVirtualMemory" call_name="1.exe" call_pid="396" call_time="12:41:06.213" err_code="5" ret_value="0" status_value="c0000022"><apiArg_list count="5"><apiArg value="148" /><apiArg value="7ffde00c" /><apiArg value="c4f75c" /><apiArg value="4" /><apiArg value="c4f724" /></apiArg_list><exInfo_list count="2"><exInfo value="WDCertM_CCB.exe" /><exInfo value="-1414676753" /></exInfo_list></action><action api_name="NtReadVirtualMemory" call_name="1.exe" call_pid="396" call_time="12:41:06.214" err_code="5" ret_value="0" status_value="c0000022"><apiArg_list count="5"><apiArg value="148" /><apiArg value="251e9c" /><apiArg value="c4f790" /><apiArg value="4" /><apiArg value="c4f72c" /></apiArg_list><exInfo_list count="2"><exInfo value="WDCertM_CCB.exe" /><exInfo value="1868" /></exInfo_list></action><action api_name="NtReadVirtualMemory" call_name="1.exe" call_pid="396" call_time="12:41:06.234" err_code="5" ret_value="0" status_value="c0000022"><apiArg_list count="5"><apiArg value="150" /><apiArg value="7ffdc00c" /><apiArg value="c4f75c" /><apiArg value="4" /><apiArg value="c4f724" /></apiArg_list><exInfo_list count="2"><exInfo value="WDKeyMonitorCCB" /><exInfo value="-1414676753" /></exInfo_list></action><action api_name="NtReadVirtualMemory" call_name="1.exe" call_pid="396" call_time="12:41:06.235" err_code="5" ret_value="0" status_value="c0000022"><apiArg_list count="5"><apiArg value="150" /><apiArg value="251e9c" /><apiArg value="c4f790" /><apiArg value="4" /><apiArg value="c4f72c" /></apiArg_list><exInfo_list count="2"><exInfo value="WDKeyMonitorCCB.exe" /><exInfo value="1880" /></exInfo_list></action><action api_name="NtReadVirtualMemory" call_name="1.exe" call_pid="396" call_time="12:41:06.255" err_code="5" ret_value="0" status_value="c0000022"><apiArg_list count="5"><apiArg value="148" /><apiArg value="7ffda00c" /><apiArg value="c4f75c" /><apiArg value="4" /><apiArg value="c4f724" /></apiArg_list><exInfo_list count="2"><exInfo value="wow.exe" /><exInfo value="-1414676753" /></exInfo_list></action><action api_name="NtReadVirtualMemory" call_name="1.exe" call_pid="396" call_time="12:41:06.256" err_code="5" ret_value="0" status_value="c0000022"><apiArg_list count="5"><apiArg value="148" /><apiArg value="251e9c" /><apiArg value="c4f790" /><apiArg value="4" /><apiArg value="c4f72c" /></apiArg_list><exInfo_list count="2"><exInfo value="wow.exe" /><exInfo value="1888" /></exInfo_list></action><action api_name="NtReadVirtualMemory" call_name="1.exe" call_pid="396" call_time="12:41:06.276" err_code="5" ret_value="0" status_value="c0000022"><apiArg_list count="5"><apiArg value="150" /><apiArg value="7ffd700c" /><apiArg value="c4f75c" /><apiArg value="4" /><apiArg value="c4f724" /></apiArg_list><exInfo_list count="2"><exInfo value="zhudongfangyu.e" /><exInfo value="-1414676753" /></exInfo_list></action><action api_name="NtReadVirtualMemory" call_name="1.exe" call_pid="396" call_time="12:41:06.277" err_code="5" ret_value="0" status_value="c0000022"><apiArg_list count="5"><apiArg value="150" /><apiArg value="251e9c" /><apiArg value="c4f790" /><apiArg value="4" /><apiArg value="c4f72c" /></apiArg_list><exInfo_list count="2"><exInfo value="zhudongfangyu.exe" /><exInfo value="1900" /></exInfo_list></action><action api_name="NtReadVirtualMemory" call_name="1.exe" call_pid="396" call_time="12:41:06.299" err_code="5" ret_value="0" status_value="c0000022"><apiArg_list count="5"><apiArg value="148" /><apiArg value="7ffd500c" /><apiArg value="c4f75c" /><apiArg value="4" /><apiArg value="c4f724" /></apiArg_list><exInfo_list count="2"><exInfo value="wscntfy.exe" /><exInfo value="1636" /></exInfo_list></action><action api_name="NtReadVirtualMemory" call_name="1.exe" call_pid="396" call_time="12:41:06.385" err_code="5" ret_value="0" status_value="c0000022"><apiArg_list count="5"><apiArg value="150" /><apiArg value="7ffd300c" /><apiArg value="c4f75c" /><apiArg value="4" /><apiArg value="c4f724" /></apiArg_list><exInfo_list count="2"><exInfo value="SyStem.exe" /><exInfo value="212" /></exInfo_list></action><action api_name="NtReadVirtualMemory" call_name="1.exe" call_pid="396" call_time="12:41:06.506" err_code="5" ret_value="0" status_value="c0000022"><apiArg_list count="5"><apiArg value="148" /><apiArg value="7ffde00c" /><apiArg value="c4f75c" /><apiArg value="4" /><apiArg value="c4f724" /></apiArg_list><exInfo_list count="2"><exInfo value="tsopool.exe" /><exInfo value="344" /></exInfo_list></action><action api_name="DnsQuery_W" call_name="1.exe" call_pid="396" call_time="12:41:04.662" err_code="0" ret_value="0" status_value="c0000034"><apiArg_list count="6"><apiArg value="e526fc" /><apiArg value="1" /><apiArg value="0" /><apiArg value="0" /><apiArg value="e4ef88" /><apiArg value="0" /></apiArg_list><exInfo_list count="1"><exInfo value="dl.static.iqiyi.com" /></exInfo_list></action><action api_name="NtQueryAttributesFile" call_name="1.exe" call_pid="396" call_time="12:41:07.569" err_code="277e" ret_value="c0000034" status_value="c0000034"><apiArg_list count="2"><apiArg value="e4ec30" /><apiArg value="e4ec08" /></apiArg_list><exInfo_list count="1"><exInfo value="C:\program\rasadhlp.dll" /></exInfo_list></action><action api_name="NtQueryAttributesFile" call_name="1.exe" call_pid="396" call_time="12:41:07.570" err_code="277e" ret_value="0" status_value="c0000034"><apiArg_list count="2"><apiArg value="e4ec30" /><apiArg value="e4ec08" /></apiArg_list><exInfo_list count="1"><exInfo value="C:\WINDOWS\system32\rasadhlp.dll" /></exInfo_list></action><action api_name="LoadLibraryExW" call_name="1.exe" call_pid="396" call_time="12:41:07.572" err_code="0" ret_value="0" status_value="0"><apiArg_list count="3"><apiArg value="0" /><apiArg value="0" /><apiArg value="0" /></apiArg_list><exInfo_list count="3"><exInfo value="C:\WINDOWS\system32\rasadhlp.dll" /><exInfo value="00076f90000" /><exInfo value="0006000" /></exInfo_list></action><action api_name="NtQueryAttributesFile" call_name="1.exe" call_pid="396" call_time="12:41:07.591" err_code="0" ret_value="0" status_value="c0000034"><apiArg_list count="2"><apiArg value="d4e7f8" /><apiArg value="d4e7d0" /></apiArg_list><exInfo_list count="1"><exInfo value="C:\WINDOWS\system32\mswsock.dll" /></exInfo_list></action><action api_name="NtQueryAttributesFile" call_name="1.exe" call_pid="396" call_time="12:41:07.592" err_code="0" ret_value="c0000034" status_value="c0000034"><apiArg_list count="2"><apiArg value="d4e7a8" /><apiArg value="d4e780" /></apiArg_list><exInfo_list count="1"><exInfo value="C:\program\hnetcfg.dll" /></exInfo_list></action><action api_name="NtQueryAttributesFile" call_name="1.exe" call_pid="396" call_time="12:41:07.593" err_code="0" ret_value="0" status_value="c0000034"><apiArg_list count="2"><apiArg value="d4e7a8" /><apiArg value="d4e780" /></apiArg_list><exInfo_list count="1"><exInfo value="C:\WINDOWS\system32\hnetcfg.dll" /></exInfo_list></action><action api_name="LoadLibraryExW" call_name="1.exe" call_pid="396" call_time="12:41:07.595" err_code="0" ret_value="0" status_value="0"><apiArg_list count="3"><apiArg value="0" /><apiArg value="0" /><apiArg value="0" /></apiArg_list><exInfo_list count="3"><exInfo value="C:\WINDOWS\system32\hnetcfg.dll" /><exInfo value="00060fd0000" /><exInfo value="00055000" /></exInfo_list></action><action api_name="NtQueryAttributesFile" call_name="1.exe" call_pid="396" call_time="12:41:07.598" err_code="3f0" ret_value="0" status_value="c000007c"><apiArg_list count="2"><apiArg value="d4e674" /><apiArg value="d4e64c" /></apiArg_list><exInfo_list count="1"><exInfo value="C:\WINDOWS\System32\mswsock.dll" /></exInfo_list></action><action api_name="NtQueryAttributesFile" call_name="1.exe" call_pid="396" call_time="12:41:07.601" err_code="3f0" ret_value="0" status_value="0"><apiArg_list count="2"><apiArg value="d4ea30" /><apiArg value="d4ea08" /></apiArg_list><exInfo_list count="1"><exInfo value="C:\WINDOWS\System32\wshtcpip.dll" /></exInfo_list></action><action api_name="LoadLibraryExW" call_name="1.exe" call_pid="396" call_time="12:41:07.606" err_code="0" ret_value="0" status_value="0"><apiArg_list count="3"><apiArg value="0" /><apiArg value="0" /><apiArg value="0" /></apiArg_list><exInfo_list count="3"><exInfo value="C:\WINDOWS\system32\wshtcpip.dll" /><exInfo value="00071a00000" /><exInfo value="0008000" /></exInfo_list></action><action api_name="WSASocketW" call_name="1.exe" call_pid="396" call_time="12:41:07.589" err_code="0" ret_value="138" status_value="0"><apiArg_list count="6"><apiArg value="2" /><apiArg value="1" /><apiArg value="0" /><apiArg value="0" /><apiArg value="0" /><apiArg value="1" /></apiArg_list><exInfo_list count="0" /></action><action api_name="NtQueryAttributesFile" call_name="1.exe" call_pid="396" call_time="12:41:07.620" err_code="0" ret_value="0" status_value="0"><apiArg_list count="2"><apiArg value="d4ea18" /><apiArg value="d4e9f0" /></apiArg_list><exInfo_list count="1"><exInfo value="C:\WINDOWS\System32\mswsock.dll" /></exInfo_list></action><action api_name="connect" call_name="1.exe" call_pid="396" call_time="12:41:07.616" err_code="2733" ret_value="ffffffff" status_value="0"><apiArg_list count="3"><apiArg value="138" /><apiArg value="d4f658" /><apiArg value="10" /></apiArg_list><exInfo_list count="1"><exInfo value="183.134.64.30: 80" /></exInfo_list></action><action api_name="send" call_name="1.exe" call_pid="396" call_time="12:41:07.641" err_code="0" ret_value="6e" status_value="0"><apiArg_list count="4"><apiArg value="138" /><apiArg value="9c4c38" /><apiArg value="6e" /><apiArg value="0" /></apiArg_list><exInfo_list count="2"><exInfo value="183.134.64.30: 80" /><exInfo value=" dl.static.iqiyi.com" /></exInfo_list></action><action api_name="recv" call_name="1.exe" call_pid="396" call_time="12:41:07.652" err_code="0" ret_value="192d" status_value="0"><apiArg_list count="4"><apiArg value="138" /><apiArg value="9c687c" /><apiArg value="4000" /><apiArg value="0" /></apiArg_list><exInfo_list count="1"><exInfo value="183.134.64.30: 80" /></exInfo_list></action><action api_name="NtQueryDirectoryFile" call_name="1.exe" call_pid="396" call_time="12:41:07.664" err_code="7a" ret_value="0" status_value="c0000034"><apiArg_list count="11"><apiArg value="138" /><apiArg value="0" /><apiArg value="0" /><apiArg value="0" /><apiArg value="d3eda0" /><apiArg value="d3edd0" /><apiArg value="268" /><apiArg value="3" /><apiArg value="1" /><apiArg value="d3edb8" /><apiArg value="0" /></apiArg_list><exInfo_list count="1"><exInfo value="C:\GpUpdate\*" /></exInfo_list></action><action api_name="NtQueryAttributesFile" call_name="1.exe" call_pid="396" call_time="12:41:07.673" err_code="7a" ret_value="c0000034" status_value="c000007c"><apiArg_list count="2"><apiArg value="d3f6ac" /><apiArg value="d3f684" /></apiArg_list><exInfo_list count="1"><exInfo value="C:\GeePlayer.exe" /></exInfo_list></action><action api_name="NtQueryAttributesFile" call_name="1.exe" call_pid="396" call_time="12:41:07.674" err_code="2" ret_value="c0000034" status_value="c0000034"><apiArg_list count="2"><apiArg value="d3f710" /><apiArg value="d3f6e8" /></apiArg_list><exInfo_list count="1"><exInfo value="C:\GpUpdate\GeePlayerSetup_update_201901161439.exe" /></exInfo_list></action><action api_name="NtQueryAttributesFile" call_name="1.exe" call_pid="396" call_time="12:41:07.748" err_code="7a" ret_value="c0000034" status_value="c000007c"><apiArg_list count="2"><apiArg value="d3f6ac" /><apiArg value="d3f684" /></apiArg_list><exInfo_list count="1"><exInfo value="C:\GeePlayer.exe" /></exInfo_list></action><action api_name="NtQueryAttributesFile" call_name="1.exe" call_pid="396" call_time="12:41:07.749" err_code="2" ret_value="c0000034" status_value="c0000034"><apiArg_list count="2"><apiArg value="d3f710" /><apiArg value="d3f6e8" /></apiArg_list><exInfo_list count="1"><exInfo value="C:\GpUpdate\GeePlayerSetup_update_201812051602.exe" /></exInfo_list></action><action api_name="NtQueryAttributesFile" call_name="1.exe" call_pid="396" call_time="12:41:07.817" err_code="0" ret_value="c0000034" status_value="c0000034"><apiArg_list count="2"><apiArg value="d3e8b4" /><apiArg value="d3e88c" /></apiArg_list><exInfo_list count="1"><exInfo value="C:\cube.dll" /></exInfo_list></action><action api_name="DnsQuery_W" call_name="1.exe" call_pid="396" call_time="12:41:07.832" err_code="0" ret_value="0" status_value="0"><apiArg_list count="6"><apiArg value="e526fc" /><apiArg value="1" /><apiArg value="0" /><apiArg value="0" /><apiArg value="108ef88" /><apiArg value="0" /></apiArg_list><exInfo_list count="1"><exInfo value="dl.static.iqiyi.com" /></exInfo_list></action><action api_name="connect" call_name="1.exe" call_pid="396" call_time="12:41:07.856" err_code="2733" ret_value="ffffffff" status_value="c0000135"><apiArg_list count="3"><apiArg value="144" /><apiArg value="d3f39c" /><apiArg value="10" /></apiArg_list><exInfo_list count="1"><exInfo value="183.134.64.30: 80" /></exInfo_list></action><action api_name="send" call_name="1.exe" call_pid="396" call_time="12:41:07.875" err_code="0" ret_value="88" status_value="c0000135"><apiArg_list count="4"><apiArg value="144" /><apiArg value="9cfd70" /><apiArg value="88" /><apiArg value="0" /></apiArg_list><exInfo_list count="2"><exInfo value="183.134.64.30: 80" /><exInfo value=" dl.static.iqiyi.com" /></exInfo_list></action><action api_name="recv" call_name="1.exe" call_pid="396" call_time="12:41:07.886" err_code="0" ret_value="2238" status_value="c0000135"><apiArg_list count="4"><apiArg value="144" /><apiArg value="9c687c" /><apiArg value="4000" /><apiArg value="0" /></apiArg_list><exInfo_list count="1"><exInfo value="183.134.64.30: 80" /></exInfo_list></action><action api_name="NtQueryAttributesFile" call_name="1.exe" call_pid="396" call_time="12:41:19.432" err_code="0" ret_value="0" status_value="c0000135"><apiArg_list count="2"><apiArg value="d3f378" /><apiArg value="d3f350" /></apiArg_list><exInfo_list count="1"><exInfo value="C:\GpUpdate" /></exInfo_list></action><action api_name="Fake_WritePEFile" call_name="1.exe" call_pid="396" call_time="12:41:19.435" err_code="0" ret_value="0" status_value="c0000135"><apiArg_list count="9"><apiArg value="144" /><apiArg value="0" /><apiArg value="0" /><apiArg value="0" /><apiArg value="d3d9f4" /><apiArg value="48b0020" /><apiArg value="1d92000" /><apiArg value="0" /><apiArg value="0" /></apiArg_list><exInfo_list count="1"><exInfo value="C:\GpUpdate\GeePlayerSetup_update_201812051602.exe" /></exInfo_list></action><action api_name="NtReadFile" call_name="1.exe" call_pid="396" call_time="12:41:19.440" err_code="0" ret_value="0" status_value="c0000135"><apiArg_list count="9"><apiArg value="144" /><apiArg value="0" /><apiArg value="0" /><apiArg value="0" /><apiArg value="d3e3f4" /><apiArg value="d52ff0" /><apiArg value="1000" /><apiArg value="0" /><apiArg value="0" /></apiArg_list><exInfo_list count="1"><exInfo value="C:\GpUpdate\GeePlayerSetup_update_201812051602.exe" /></exInfo_list></action><action api_name="NtReadFile" call_name="1.exe" call_pid="396" call_time="12:41:25.586" err_code="3f0" ret_value="0" status_value="c000007c"><apiArg_list count="9"><apiArg value="144" /><apiArg value="0" /><apiArg value="0" /><apiArg value="0" /><apiArg value="d3f0b4" /><apiArg value="f90000" /><apiArg value="0" /><apiArg value="0" /><apiArg value="7c885604" /></apiArg_list><exInfo_list count="1"><exInfo value="C:\GpUpdate.ini" /></exInfo_list></action><action api_name="NtWriteFile" call_name="1.exe" call_pid="396" call_time="12:41:25.587" err_code="3f0" ret_value="0" status_value="c000007c"><apiArg_list count="9"><apiArg value="144" /><apiArg value="0" /><apiArg value="0" /><apiArg value="0" /><apiArg value="d3f0b8" /><apiArg value="f90000" /><apiArg value="41" /><apiArg value="d3f0c8" /><apiArg value="7c885604" /></apiArg_list><exInfo_list count="1"><exInfo value="C:\GpUpdate.ini" /></exInfo_list></action><action api_name="NtTerminateProcess" call_name="1.exe" call_pid="396" call_time="12:41:25.664" err_code="abadbeef" ret_value="abadbeef" status_value="abadbeef"><apiArg_list count="2"><apiArg value="0" /><apiArg value="0" /></apiArg_list><exInfo_list count="2"><exInfo value="1.exe" /><exInfo value="396" /></exInfo_list></action><action api_name="AnalyzeStop" call_name="" call_pid="0" call_time="12:45:57.717" err_code="0" ret_value="0" status_value="0"><apiArg_list count="0" /><exInfo_list count="0" /></action></action_list></start_boot></file></file_list></report>